{
"meta":{"test_sets":[],"test_metrics":[],"learn_metrics":[{"best_value":"Min","name":"Logloss"}],"launch_mode":"Train","parameters":"","iteration_count":1000,"learn_sets":["learn"],"name":"experiment"},
"iterations":[
{"learn":[0.6812707199],"iteration":0,"passed_time":0.005796271633,"remaining_time":5.790475361},
{"learn":[0.6692553676],"iteration":1,"passed_time":0.01110221495,"remaining_time":5.54000526},
{"learn":[0.6583999847],"iteration":2,"passed_time":0.01564574598,"remaining_time":5.199602915},
{"learn":[0.6482153566],"iteration":3,"passed_time":0.02059644467,"remaining_time":5.128514724},
{"learn":[0.6375284895],"iteration":4,"passed_time":0.02627845577,"remaining_time":5.229412699},
{"learn":[0.6284121547],"iteration":5,"passed_time":0.03102438874,"remaining_time":5.139707068},
{"learn":[0.6165949672],"iteration":6,"passed_time":0.03545537396,"remaining_time":5.029598049},
{"learn":[0.6064602073],"iteration":7,"passed_time":0.04043495766,"remaining_time":5.01393475},
{"learn":[0.5955532344],"iteration":8,"passed_time":0.04562237827,"remaining_time":5.023530763},
{"learn":[0.5862556376],"iteration":9,"passed_time":0.05007539046,"remaining_time":4.957463656},
{"learn":[0.5759064217],"iteration":10,"passed_time":0.0541861121,"remaining_time":4.871824079},
{"learn":[0.5665625775],"iteration":11,"passed_time":0.06018261177,"remaining_time":4.955035035},
{"learn":[0.5565223171],"iteration":12,"passed_time":0.06438344849,"remaining_time":4.888189512},
{"learn":[0.5480548891],"iteration":13,"passed_time":0.06824023941,"remaining_time":4.806062575},
{"learn":[0.5396360306],"iteration":14,"passed_time":0.07497726379,"remaining_time":4.923506989},
{"learn":[0.5311918682],"iteration":15,"passed_time":0.07974002746,"remaining_time":4.904011689},
{"learn":[0.5238194102],"iteration":16,"passed_time":0.08361083892,"remaining_time":4.834673804},
{"learn":[0.5156164582],"iteration":17,"passed_time":0.08824232148,"remaining_time":4.814108872},
{"learn":[0.5084395316],"iteration":18,"passed_time":0.09224054115,"remaining_time":4.762524783},
{"learn":[0.5008457061],"iteration":19,"passed_time":0.09611244392,"remaining_time":4.709509752},
{"learn":[0.4942122028],"iteration":20,"passed_time":0.09982515022,"remaining_time":4.653753432},
{"learn":[0.4861539522],"iteration":21,"passed_time":0.106060863,"remaining_time":4.714887455},
{"learn":[0.477926472],"iteration":22,"passed_time":0.1110490211,"remaining_time":4.717169288},
{"learn":[0.4707442082],"iteration":23,"passed_time":0.115773002,"remaining_time":4.708102081},
{"learn":[0.4627743414],"iteration":24,"passed_time":0.1217463424,"remaining_time":4.748107355},
{"learn":[0.4549290157],"iteration":25,"passed_time":0.1268209773,"remaining_time":4.750908918},
{"learn":[0.4489933622],"iteration":26,"passed_time":0.1315150087,"remaining_time":4.739411241},
{"learn":[0.4428931378],"iteration":27,"passed_time":0.1377253371,"remaining_time":4.781036702},
{"learn":[0.4359717626],"iteration":28,"passed_time":0.1421820249,"remaining_time":4.760646419},
{"learn":[0.4284913615],"iteration":29,"passed_time":0.1464431584,"remaining_time":4.734995455},
{"learn":[0.4217828555],"iteration":30,"passed_time":0.1504512667,"remaining_time":4.702815402},
{"learn":[0.4164147437],"iteration":31,"passed_time":0.1548974672,"remaining_time":4.685648384},
{"learn":[0.4115147671],"iteration":32,"passed_time":0.1587358199,"remaining_time":4.65144054},
{"learn":[0.4066812621],"iteration":33,"passed_time":0.1626200028,"remaining_time":4.620321257},
{"learn":[0.3998871197],"iteration":34,"passed_time":0.1666132293,"remaining_time":4.593764752},
{"learn":[0.3938984327],"iteration":35,"passed_time":0.1710043901,"remaining_time":4.579117557},
{"learn":[0.3875134456],"iteration":36,"passed_time":0.1748913381,"remaining_time":4.551901584},
{"learn":[0.3824591285],"iteration":37,"passed_time":0.1786828411,"remaining_time":4.523497189},
{"learn":[0.3763857142],"iteration":38,"passed_time":0.1827683298,"remaining_time":4.5035991},
{"learn":[0.3713417939],"iteration":39,"passed_time":0.1871880388,"remaining_time":4.492512931},
{"learn":[0.3659137224],"iteration":40,"passed_time":0.1910356584,"remaining_time":4.468370643},
{"learn":[0.3604578711],"iteration":41,"passed_time":0.195020737,"remaining_time":4.448330143},
{"learn":[0.3549807062],"iteration":42,"passed_time":0.1992441533,"remaining_time":4.434340808},
{"learn":[0.3502936524],"iteration":43,"passed_time":0.2033160004,"remaining_time":4.417502189},
{"learn":[0.3459277993],"iteration":44,"passed_time":0.2070660941,"remaining_time":4.394402664},
{"learn":[0.3413650416],"iteration":45,"passed_time":0.2110237112,"remaining_time":4.376448271},
{"learn":[0.3370705118],"iteration":46,"passed_time":0.2169414117,"remaining_time":4.398833304},
{"learn":[0.3322899979],"iteration":47,"passed_time":0.220786547,"remaining_time":4.378933183},
{"learn":[0.3284171218],"iteration":48,"passed_time":0.2249482725,"remaining_time":4.365832799},
{"learn":[0.323848908],"iteration":49,"passed_time":0.2289123153,"remaining_time":4.349333991},
{"learn":[0.3196788123],"iteration":50,"passed_time":0.234512981,"remaining_time":4.363780765},
{"learn":[0.3155396032],"iteration":51,"passed_time":0.2393666288,"remaining_time":4.363837771},
{"learn":[0.3115143035],"iteration":52,"passed_time":0.2432828788,"remaining_time":4.346960118},
{"learn":[0.3067927201],"iteration":53,"passed_time":0.2480690239,"remaining_time":4.345801788},
{"learn":[0.303194335],"iteration":54,"passed_time":0.2529975591,"remaining_time":4.34695806},
{"learn":[0.2995448467],"iteration":55,"passed_time":0.2559173142,"remaining_time":4.314034725},
{"learn":[0.2957797991],"iteration":56,"passed_time":0.2599504615,"remaining_time":4.300583951},
{"learn":[0.2922001654],"iteration":57,"passed_time":0.2661378334,"remaining_time":4.3224455},
{"learn":[0.2879279241],"iteration":58,"passed_time":0.2701893371,"remaining_time":4.309290952},
{"learn":[0.284066461],"iteration":59,"passed_time":0.2746223663,"remaining_time":4.302417072},
{"learn":[0.2796158338],"iteration":60,"passed_time":0.2788526482,"remaining_time":4.29250224},
{"learn":[0.2762531768],"iteration":61,"passed_time":0.2831744649,"remaining_time":4.284155614},
{"learn":[0.2726670149],"iteration":62,"passed_time":0.2868942373,"remaining_time":4.266982546},
{"learn":[0.2695643082],"iteration":63,"passed_time":0.2908166028,"remaining_time":4.253192816},
{"learn":[0.2662647085],"iteration":64,"passed_time":0.2955239255,"remaining_time":4.250998005},
{"learn":[0.2633617698],"iteration":65,"passed_time":0.2995286958,"remaining_time":4.238784877},
{"learn":[0.2598971823],"iteration":66,"passed_time":0.3034132068,"remaining_time":4.225142119},
{"learn":[0.2562218825],"iteration":67,"passed_time":0.3073394212,"remaining_time":4.21235795},
{"learn":[0.2526903697],"iteration":68,"passed_time":0.3126635691,"remaining_time":4.218692505},
{"learn":[0.2506041183],"iteration":69,"passed_time":0.3167176339,"remaining_time":4.207819993},
{"learn":[0.2474009757],"iteration":70,"passed_time":0.3205102332,"remaining_time":4.193718403},
{"learn":[0.2445813208],"iteration":71,"passed_time":0.3250775949,"remaining_time":4.189889001},
{"learn":[0.2414788828],"iteration":72,"passed_time":0.3305753912,"remaining_time":4.197854625},
{"learn":[0.2391356583],"iteration":73,"passed_time":0.334670754,"remaining_time":4.187907003},
{"learn":[0.2365760147],"iteration":74,"passed_time":0.3386165249,"remaining_time":4.176270473},
{"learn":[0.2343239197],"iteration":75,"passed_time":0.3429180008,"remaining_time":4.169160957},
{"learn":[0.231528244],"iteration":76,"passed_time":0.3474375051,"remaining_time":4.164737886},
{"learn":[0.2283836937],"iteration":77,"passed_time":0.3515959472,"remaining_time":4.156044401},
{"learn":[0.2256464971],"iteration":78,"passed_time":0.3552931341,"remaining_time":4.142088311},
{"learn":[0.2235548211],"iteration":79,"passed_time":0.36022366,"remaining_time":4.14257209},
{"learn":[0.2206440402],"iteration":80,"passed_time":0.3644307177,"remaining_time":4.134713945},
{"learn":[0.2181184226],"iteration":81,"passed_time":0.3682439742,"remaining_time":4.122536199},
{"learn":[0.2154115091],"iteration":82,"passed_time":0.3719973795,"remaining_time":4.109898759},
{"learn":[0.2131578533],"iteration":83,"passed_time":0.3771394311,"remaining_time":4.112615701},
{"learn":[0.2114795556],"iteration":84,"passed_time":0.3809273905,"remaining_time":4.100571321},
{"learn":[0.2093100653],"iteration":85,"passed_time":0.3848949223,"remaining_time":4.09062743},
{"learn":[0.2068974344],"iteration":86,"passed_time":0.3887545995,"remaining_time":4.079689073},
{"learn":[0.2045982076],"iteration":87,"passed_time":0.3935633594,"remaining_time":4.078747543},
{"learn":[0.2023963193],"iteration":88,"passed_time":0.3973458354,"remaining_time":4.067214113},
{"learn":[0.2003862696],"iteration":89,"passed_time":0.4011529711,"remaining_time":4.056102263},
{"learn":[0.1987960034],"iteration":90,"passed_time":0.4051382851,"remaining_time":4.046930782},
{"learn":[0.1969810429],"iteration":91,"passed_time":0.410171047,"remaining_time":4.048209898},
{"learn":[0.1950240502],"iteration":92,"passed_time":0.4139456738,"remaining_time":4.037083076},
{"learn":[0.1934985402],"iteration":93,"passed_time":0.4176826343,"remaining_time":4.025749646},
{"learn":[0.1915833044],"iteration":94,"passed_time":0.4225151806,"remaining_time":4.025013036},
{"learn":[0.1895685625],"iteration":95,"passed_time":0.4267745601,"remaining_time":4.018793774},
{"learn":[0.1878410395],"iteration":96,"passed_time":0.4307387038,"remaining_time":4.00986649},
{"learn":[0.1858975955],"iteration":97,"passed_time":0.4344289021,"remaining_time":3.998519078},
{"learn":[0.18366375],"iteration":98,"passed_time":0.4401337017,"remaining_time":4.005661265},
{"learn":[0.1822655185],"iteration":99,"passed_time":0.4452385673,"remaining_time":4.007147106},
{"learn":[0.1805124657],"iteration":100,"passed_time":0.449101973,"remaining_time":3.997452215},
{"learn":[0.1788197341],"iteration":101,"passed_time":0.4539516751,"remaining_time":3.996554943},
{"learn":[0.1775930075],"iteration":102,"passed_time":0.4596086782,"remaining_time":4.002611499},
{"learn":[0.1760762667],"iteration":103,"passed_time":0.4636861819,"remaining_time":3.994834798},
{"learn":[0.1743819866],"iteration":104,"passed_time":0.4678100144,"remaining_time":3.987523456},
{"learn":[0.1728424415],"iteration":105,"passed_time":0.4734883152,"remaining_time":3.993382583},
{"learn":[0.1711106427],"iteration":106,"passed_time":0.477690098,"remaining_time":3.986703341},
{"learn":[0.1694327118],"iteration":107,"passed_time":0.4816203016,"remaining_time":3.977826935},
{"learn":[0.168204396],"iteration":108,"passed_time":0.4857662239,"remaining_time":3.970804638},
{"learn":[0.1661647787],"iteration":109,"passed_time":0.4908533226,"remaining_time":3.97144961},
{"learn":[0.1646918004],"iteration":110,"passed_time":0.4949433978,"remaining_time":3.964006132},
{"learn":[0.1628624811],"iteration":111,"passed_time":0.4988669518,"remaining_time":3.95530226},
{"learn":[0.1618148422],"iteration":112,"passed_time":0.5043101105,"remaining_time":3.958611221},
{"learn":[0.1603725928],"iteration":113,"passed_time":0.5081779794,"remaining_time":3.949523594},
{"learn":[0.1587528738],"iteration":114,"passed_time":0.5119236434,"remaining_time":3.9395863},
{"learn":[0.1573936867],"iteration":115,"passed_time":0.5157769615,"remaining_time":3.930576155},
{"learn":[0.1562148273],"iteration":116,"passed_time":0.5207081964,"remaining_time":3.929789209},
{"learn":[0.1544954257],"iteration":117,"passed_time":0.524828762,"remaining_time":3.922872611},
{"learn":[0.1527883086],"iteration":118,"passed_time":0.528637751,"remaining_time":3.913696291},
{"learn":[0.1516179135],"iteration":119,"passed_time":0.5326902215,"remaining_time":3.906394958},
{"learn":[0.1502728193],"iteration":120,"passed_time":0.53809707,"remaining_time":3.908986153},
{"learn":[0.1490203454],"iteration":121,"passed_time":0.5422799934,"remaining_time":3.902637986},
{"learn":[0.1480586787],"iteration":122,"passed_time":0.5460691587,"remaining_time":3.893517498},
{"learn":[0.1473415287],"iteration":123,"passed_time":0.5507076545,"remaining_time":3.890483107},
{"learn":[0.1462843501],"iteration":124,"passed_time":0.5547583701,"remaining_time":3.883308591},
{"learn":[0.1449180746],"iteration":125,"passed_time":0.5586692249,"remaining_time":3.875213512},
{"learn":[0.1438272212],"iteration":126,"passed_time":0.562484245,"remaining_time":3.866525558},
{"learn":[0.1426049315],"iteration":127,"passed_time":0.567658937,"remaining_time":3.867176508},
{"learn":[0.1410792306],"iteration":128,"passed_time":0.571644876,"remaining_time":3.859710752},
{"learn":[0.1396660965],"iteration":129,"passed_time":0.5754015163,"remaining_time":3.850763994},
{"learn":[0.1389048936],"iteration":130,"passed_time":0.5793002386,"remaining_time":3.842838987},
{"learn":[0.1378030596],"iteration":131,"passed_time":0.5848117717,"remaining_time":3.845580438},
{"learn":[0.1364358269],"iteration":132,"passed_time":0.5885935866,"remaining_time":3.836922102},
{"learn":[0.1353260865],"iteration":133,"passed_time":0.5925003774,"remaining_time":3.82914423},
{"learn":[0.1344647968],"iteration":134,"passed_time":0.5964202926,"remaining_time":3.821507801},
{"learn":[0.1336502496],"iteration":135,"passed_time":0.6016344856,"remaining_time":3.822148496},
{"learn":[0.1325486987],"iteration":136,"passed_time":0.6054195033,"remaining_time":3.813700959},
{"learn":[0.1314185977],"iteration":137,"passed_time":0.6092926475,"remaining_time":3.805871465},
{"learn":[0.1302982685],"iteration":138,"passed_time":0.6137534245,"remaining_time":3.801738838},
{"learn":[0.1291763329],"iteration":139,"passed_time":0.618871492,"remaining_time":3.801639165},
{"learn":[0.1280232843],"iteration":140,"passed_time":0.6226571091,"remaining_time":3.793350757},
{"learn":[0.1270254864],"iteration":141,"passed_time":0.6265403952,"remaining_time":3.785715909},
{"learn":[0.1262965614],"iteration":142,"passed_time":0.6331764354,"remaining_time":3.794630805},
{"learn":[0.1253371459],"iteration":143,"passed_time":0.6382273339,"remaining_time":3.793906929},
{"learn":[0.1241785403],"iteration":144,"passed_time":0.6422331918,"remaining_time":3.786961235},
{"learn":[0.1233555872],"iteration":145,"passed_time":0.6482666367,"remaining_time":3.791915807},
{"learn":[0.1222516234],"iteration":146,"passed_time":0.6523978133,"remaining_time":3.78568255},
{"learn":[0.1213364321],"iteration":147,"passed_time":0.656468586,"remaining_time":3.779129968},
{"learn":[0.1206069783],"iteration":148,"passed_time":0.6611701204,"remaining_time":3.776213238},
{"learn":[0.1199748105],"iteration":149,"passed_time":0.6668288776,"remaining_time":3.778696973},
{"learn":[0.1192377441],"iteration":150,"passed_time":0.671470411,"remaining_time":3.775353503},
{"learn":[0.1184486551],"iteration":151,"passed_time":0.6753533405,"remaining_time":3.767760742},
{"learn":[0.1177390593],"iteration":152,"passed_time":0.6808170414,"remaining_time":3.768967543},
{"learn":[0.1170419171],"iteration":153,"passed_time":0.6846722533,"remaining_time":3.76125147},
{"learn":[0.1159826039],"iteration":154,"passed_time":0.6887053899,"remaining_time":3.75455519},
{"learn":[0.1150862522],"iteration":155,"passed_time":0.6924873112,"remaining_time":3.746533915},
{"learn":[0.1143076348],"iteration":156,"passed_time":0.6976102059,"remaining_time":3.745766902},
{"learn":[0.113516293],"iteration":157,"passed_time":0.7015853537,"remaining_time":3.738828277},
{"learn":[0.1129238214],"iteration":158,"passed_time":0.7054696388,"remaining_time":3.731446329},
{"learn":[0.1122398906],"iteration":159,"passed_time":0.7095451804,"remaining_time":3.725112197},
{"learn":[0.111475108],"iteration":160,"passed_time":0.7139068981,"remaining_time":3.720297438},
{"learn":[0.1105260963],"iteration":161,"passed_time":0.7177157878,"remaining_time":3.712628581},
{"learn":[0.1098917019],"iteration":162,"passed_time":0.7215454345,"remaining_time":3.705113673},
{"learn":[0.1089100996],"iteration":163,"passed_time":0.7256202393,"remaining_time":3.698893415},
{"learn":[0.1081243736],"iteration":164,"passed_time":0.7300860497,"remaining_time":3.694677888},
{"learn":[0.1074185415],"iteration":165,"passed_time":0.7340536435,"remaining_time":3.687956257},
{"learn":[0.1068274391],"iteration":166,"passed_time":0.7379146801,"remaining_time":3.680736099},
{"learn":[0.1060182072],"iteration":167,"passed_time":0.7429800207,"remaining_time":3.679520103},
{"learn":[0.1053244102],"iteration":168,"passed_time":0.7479321768,"remaining_time":3.677702006},
{"learn":[0.1044933764],"iteration":169,"passed_time":0.7530585349,"remaining_time":3.676697553},
{"learn":[0.1037332632],"iteration":170,"passed_time":0.7575045811,"remaining_time":3.67234677},
{"learn":[0.1028418304],"iteration":171,"passed_time":0.7619091816,"remaining_time":3.667795362},
{"learn":[0.1024387624],"iteration":172,"passed_time":0.7658300872,"remaining_time":3.660933423},
{"learn":[0.1015548478],"iteration":173,"passed_time":0.7697669572,"remaining_time":3.654181073},
{"learn":[0.1010071783],"iteration":174,"passed_time":0.7737472048,"remaining_time":3.647665394},
{"learn":[0.1001849159],"iteration":175,"passed_time":0.7780636073,"remaining_time":3.642752343},
{"learn":[0.09955519045],"iteration":176,"passed_time":0.7819121336,"remaining_time":3.635670542},
{"learn":[0.09886513113],"iteration":177,"passed_time":0.7857129565,"remaining_time":3.628404777},
{"learn":[0.09828408115],"iteration":178,"passed_time":0.7896574408,"remaining_time":3.621836642},
{"learn":[0.09769441831],"iteration":179,"passed_time":0.7940965888,"remaining_time":3.617551127},
{"learn":[0.09713931121],"iteration":180,"passed_time":0.7980227689,"remaining_time":3.610942805},
{"learn":[0.09677283135],"iteration":181,"passed_time":0.8018612489,"remaining_time":3.603969789},
{"learn":[0.09616703794],"iteration":182,"passed_time":0.8062822549,"remaining_time":3.599631706},
{"learn":[0.09541274971],"iteration":183,"passed_time":0.8104442422,"remaining_time":3.594144031},
{"learn":[0.0947287314],"iteration":184,"passed_time":0.8141932542,"remaining_time":3.586851363},
{"learn":[0.09415655374],"iteration":185,"passed_time":0.8180484115,"remaining_time":3.580061328},
{"learn":[0.09356683951],"iteration":186,"passed_time":0.8233778648,"remaining_time":3.579712321},
{"learn":[0.09308716963],"iteration":187,"passed_time":0.8274583768,"remaining_time":3.573915968},
{"learn":[0.0925404662],"iteration":188,"passed_time":0.8314474508,"remaining_time":3.567745411},
{"learn":[0.09177201272],"iteration":189,"passed_time":0.8352027747,"remaining_time":3.560601303},
{"learn":[0.09106763269],"iteration":190,"passed_time":0.8410239774,"remaining_time":3.56224292},
{"learn":[0.09062656146],"iteration":191,"passed_time":0.8457748311,"remaining_time":3.559302414},
{"learn":[0.09024392276],"iteration":192,"passed_time":0.8497424478,"remaining_time":3.553068162},
{"learn":[0.08980339377],"iteration":193,"passed_time":0.8553999279,"remaining_time":3.553878051},
{"learn":[0.08929144827],"iteration":194,"passed_time":0.8595895108,"remaining_time":3.548561826},
{"learn":[0.08877058267],"iteration":195,"passed_time":0.8633373355,"remaining_time":3.541444988},
{"learn":[0.08815899737],"iteration":196,"passed_time":0.8673648931,"remaining_time":3.535502585},
{"learn":[0.08767718168],"iteration":197,"passed_time":0.8738940136,"remaining_time":3.539712116},
{"learn":[0.087227842],"iteration":198,"passed_time":0.8779293514,"remaining_time":3.533775932},
{"learn":[0.08672082298],"iteration":199,"passed_time":0.8816703772,"remaining_time":3.526681509},
{"learn":[0.08606617439],"iteration":200,"passed_time":0.8884982609,"remaining_time":3.531891097},
{"learn":[0.0856647201],"iteration":201,"passed_time":0.8928928089,"remaining_time":3.527368621},
{"learn":[0.08518973103],"iteration":202,"passed_time":0.896770358,"remaining_time":3.520817613},
{"learn":[0.08485251842],"iteration":203,"passed_time":0.9011753888,"remaining_time":3.516351027},
{"learn":[0.08438492786],"iteration":204,"passed_time":0.9056288767,"remaining_time":3.512072961},
{"learn":[0.08388872617],"iteration":205,"passed_time":0.9094544085,"remaining_time":3.505372817},
{"learn":[0.08335761328],"iteration":206,"passed_time":0.9133902919,"remaining_time":3.499123195},
{"learn":[0.08281249137],"iteration":207,"passed_time":0.9183664826,"remaining_time":3.496856991},
{"learn":[0.08248679418],"iteration":208,"passed_time":0.9223703751,"remaining_time":3.490885008},
{"learn":[0.0820218893],"iteration":209,"passed_time":0.9261564427,"remaining_time":3.484112332},
{"learn":[0.08159009415],"iteration":210,"passed_time":0.9304057246,"remaining_time":3.479100079},
{"learn":[0.08110385036],"iteration":211,"passed_time":0.9357476981,"remaining_time":3.478156538},
{"learn":[0.08065735825],"iteration":212,"passed_time":0.9403043967,"remaining_time":3.474270236},
{"learn":[0.08026272255],"iteration":213,"passed_time":0.9444063896,"remaining_time":3.46870758},
{"learn":[0.07967296082],"iteration":214,"passed_time":0.9483337768,"remaining_time":3.462520999},
{"learn":[0.07940603128],"iteration":215,"passed_time":0.9534113103,"remaining_time":3.460529941},
{"learn":[0.07887133167],"iteration":216,"passed_time":0.9572347642,"remaining_time":3.453985347},
{"learn":[0.07847176874],"iteration":217,"passed_time":0.9611109245,"remaining_time":3.447654784},
{"learn":[0.07807677069],"iteration":218,"passed_time":0.9653199733,"remaining_time":3.442533786},
{"learn":[0.07752599864],"iteration":219,"passed_time":0.9699163387,"remaining_time":3.438794292},
{"learn":[0.07725170795],"iteration":220,"passed_time":0.9737621029,"remaining_time":3.432401259},
{"learn":[0.07694632458],"iteration":221,"passed_time":0.9775962575,"remaining_time":3.425990488},
{"learn":[0.07646201987],"iteration":222,"passed_time":0.9823079896,"remaining_time":3.422660574},
{"learn":[0.07603093798],"iteration":223,"passed_time":0.9862785674,"remaining_time":3.416750751},
{"learn":[0.07574344562],"iteration":224,"passed_time":0.990148185,"remaining_time":3.410510415},
{"learn":[0.07531793597],"iteration":225,"passed_time":0.9939641863,"remaining_time":3.404107434},
{"learn":[0.07486713106],"iteration":226,"passed_time":0.9991372529,"remaining_time":3.402348443},
{"learn":[0.07446228657],"iteration":227,"passed_time":1.003074112,"remaining_time":3.396373748},
{"learn":[0.07414075418],"iteration":228,"passed_time":1.006934243,"remaining_time":3.390158522},
{"learn":[0.07376933761],"iteration":229,"passed_time":1.010716983,"remaining_time":3.383704681},
{"learn":[0.07348674035],"iteration":230,"passed_time":1.016649421,"remaining_time":3.384430323},
{"learn":[0.07298807761],"iteration":231,"passed_time":1.02071685,"remaining_time":3.378924746},
{"learn":[0.07255791714],"iteration":232,"passed_time":1.024680211,"remaining_time":3.373088936},
{"learn":[0.07208409788],"iteration":233,"passed_time":1.029220412,"remaining_time":3.369157418},
{"learn":[0.07171853794],"iteration":234,"passed_time":1.034352464,"remaining_time":3.367147384},
{"learn":[0.07140825468],"iteration":235,"passed_time":1.03861033,"remaining_time":3.362280898},
{"learn":[0.07092668923],"iteration":236,"passed_time":1.042730235,"remaining_time":3.356975397},
{"learn":[0.07061574919],"iteration":237,"passed_time":1.048590952,"remaining_time":3.357253386},
{"learn":[0.07028530671],"iteration":238,"passed_time":1.05319961,"remaining_time":3.35349332},
{"learn":[0.06993390477],"iteration":239,"passed_time":1.056990716,"remaining_time":3.347137268},
{"learn":[0.06951197584],"iteration":240,"passed_time":1.062161521,"remaining_time":3.345147696},
{"learn":[0.06919867971],"iteration":241,"passed_time":1.068778724,"remaining_time":3.347662285},
{"learn":[0.06880396385],"iteration":242,"passed_time":1.074516984,"remaining_time":3.347363609},
{"learn":[0.06850348924],"iteration":243,"passed_time":1.080874443,"remaining_time":3.348938847},
{"learn":[0.06823837931],"iteration":244,"passed_time":1.086079795,"remaining_time":3.346898959},
{"learn":[0.06794739014],"iteration":245,"passed_time":1.090692734,"remaining_time":3.343017565},
{"learn":[0.06765429274],"iteration":246,"passed_time":1.099810065,"remaining_time":3.352862262},
{"learn":[0.06741857563],"iteration":247,"passed_time":1.105330439,"remaining_time":3.351647137},
{"learn":[0.06709105603],"iteration":248,"passed_time":1.111783896,"remaining_time":3.353211669},
{"learn":[0.06681289792],"iteration":249,"passed_time":1.116512173,"remaining_time":3.34953652},
{"learn":[0.0664513043],"iteration":250,"passed_time":1.120997144,"remaining_time":3.345126937},
{"learn":[0.06610928846],"iteration":251,"passed_time":1.126514326,"remaining_time":3.343780618},
{"learn":[0.06582031938],"iteration":252,"passed_time":1.132330219,"remaining_time":3.343283295},
{"learn":[0.06555368784],"iteration":253,"passed_time":1.137309511,"remaining_time":3.340286989},
{"learn":[0.06521326662],"iteration":254,"passed_time":1.142648762,"remaining_time":3.338326775},
{"learn":[0.06491214906],"iteration":255,"passed_time":1.147803152,"remaining_time":3.335802909},
{"learn":[0.06456266461],"iteration":256,"passed_time":1.153287925,"remaining_time":3.334213729},
{"learn":[0.06414762658],"iteration":257,"passed_time":1.158811302,"remaining_time":3.332705373},
{"learn":[0.06379592854],"iteration":258,"passed_time":1.163143023,"remaining_time":3.327756679},
{"learn":[0.06360311015],"iteration":259,"passed_time":1.167957056,"remaining_time":3.324185467},
{"learn":[0.06331177005],"iteration":260,"passed_time":1.172318213,"remaining_time":3.31932245},
{"learn":[0.06304490974],"iteration":261,"passed_time":1.177070081,"remaining_time":3.315563816},
{"learn":[0.06274413923],"iteration":262,"passed_time":1.180857841,"remaining_time":3.309095927},
{"learn":[0.06256096281],"iteration":263,"passed_time":1.185238254,"remaining_time":3.304300586},
{"learn":[0.06238287797],"iteration":264,"passed_time":1.190106259,"remaining_time":3.300860756},
{"learn":[0.0619286025],"iteration":265,"passed_time":1.194214008,"remaining_time":3.295312339},
{"learn":[0.06163298162],"iteration":266,"passed_time":1.198139969,"remaining_time":3.289275645},
{"learn":[0.06135584771],"iteration":267,"passed_time":1.20234013,"remaining_time":3.28400364},
{"learn":[0.06103369919],"iteration":268,"passed_time":1.208899081,"remaining_time":3.285149546},
{"learn":[0.06071307333],"iteration":269,"passed_time":1.212939875,"remaining_time":3.279430033},
{"learn":[0.06043996128],"iteration":270,"passed_time":1.217881121,"remaining_time":3.276145157},
{"learn":[0.06009970234],"iteration":271,"passed_time":1.221955059,"remaining_time":3.270526775},
{"learn":[0.05986241973],"iteration":272,"passed_time":1.22645449,"remaining_time":3.266052799},
{"learn":[0.0595194596],"iteration":273,"passed_time":1.230285645,"remaining_time":3.259807949},
{"learn":[0.05924665302],"iteration":274,"passed_time":1.235957432,"remaining_time":3.25843323},
{"learn":[0.05892392469],"iteration":275,"passed_time":1.240647979,"remaining_time":3.254453395},
{"learn":[0.05864716493],"iteration":276,"passed_time":1.244928875,"remaining_time":3.249399193},
{"learn":[0.05835729241],"iteration":277,"passed_time":1.251146721,"remaining_time":3.249381054},
{"learn":[0.058124391],"iteration":278,"passed_time":1.25590253,"remaining_time":3.245540231},
{"learn":[0.05790942316],"iteration":279,"passed_time":1.259899022,"remaining_time":3.239740341},
{"learn":[0.0577386103],"iteration":280,"passed_time":1.266173793,"remaining_time":3.239782765},
{"learn":[0.05746549067],"iteration":281,"passed_time":1.271164914,"remaining_time":3.236512085},
{"learn":[0.05719077951],"iteration":282,"passed_time":1.275488288,"remaining_time":3.231537464},
{"learn":[0.0568741421],"iteration":283,"passed_time":1.280363596,"remaining_time":3.227958926},
{"learn":[0.05660667863],"iteration":284,"passed_time":1.286083237,"remaining_time":3.226489526},
{"learn":[0.05639129324],"iteration":285,"passed_time":1.290347261,"remaining_time":3.221356449},
{"learn":[0.05619616748],"iteration":286,"passed_time":1.29464233,"remaining_time":3.216306555},
{"learn":[0.05595614738],"iteration":287,"passed_time":1.299830682,"remaining_time":3.213470297},
{"learn":[0.05563389739],"iteration":288,"passed_time":1.30364045,"remaining_time":3.207226158},
{"learn":[0.05541565729],"iteration":289,"passed_time":1.308145515,"remaining_time":3.202701088},
{"learn":[0.05513088985],"iteration":290,"passed_time":1.312534701,"remaining_time":3.197893825},
{"learn":[0.05487038393],"iteration":291,"passed_time":1.317114967,"remaining_time":3.193552727},
{"learn":[0.05455976426],"iteration":292,"passed_time":1.320884453,"remaining_time":3.187253613},
{"learn":[0.05428901289],"iteration":293,"passed_time":1.325074889,"remaining_time":3.181982557},
{"learn":[0.05409916844],"iteration":294,"passed_time":1.331026458,"remaining_time":3.180927638},
{"learn":[0.05381727109],"iteration":295,"passed_time":1.335822666,"remaining_time":3.177091747},
{"learn":[0.05363987503],"iteration":296,"passed_time":1.339764069,"remaining_time":3.171226062},
{"learn":[0.05333465542],"iteration":297,"passed_time":1.344226614,"remaining_time":3.166600949},
{"learn":[0.05309045951],"iteration":298,"passed_time":1.349147557,"remaining_time":3.163051631},
{"learn":[0.05274274804],"iteration":299,"passed_time":1.353579298,"remaining_time":3.158351696},
{"learn":[0.05254474703],"iteration":300,"passed_time":1.358038928,"remaining_time":3.153718307},
{"learn":[0.05226693914],"iteration":301,"passed_time":1.364669557,"remaining_time":3.154103811},
{"learn":[0.0520925614],"iteration":302,"passed_time":1.368648719,"remaining_time":3.148343753},
{"learn":[0.05193401297],"iteration":303,"passed_time":1.372789705,"remaining_time":3.142965903},
{"learn":[0.05170933648],"iteration":304,"passed_time":1.377953084,"remaining_time":3.13992588},
{"learn":[0.05146075339],"iteration":305,"passed_time":1.381999312,"remaining_time":3.134338309},
{"learn":[0.05125313464],"iteration":306,"passed_time":1.386067724,"remaining_time":3.128810855},
{"learn":[0.05106716045],"iteration":307,"passed_time":1.390349245,"remaining_time":3.123771681},
{"learn":[0.05078515866],"iteration":308,"passed_time":1.395561603,"remaining_time":3.120818989},
{"learn":[0.05065478543],"iteration":309,"passed_time":1.399654062,"remaining_time":3.115359042},
{"learn":[0.05046670948],"iteration":310,"passed_time":1.403682761,"remaining_time":3.109766631},
{"learn":[0.05025805967],"iteration":311,"passed_time":1.407643427,"remaining_time":3.104034225},
{"learn":[0.05009939147],"iteration":312,"passed_time":1.413400249,"remaining_time":3.102255499},
{"learn":[0.04981749424],"iteration":313,"passed_time":1.417513604,"remaining_time":3.096860931},
{"learn":[0.04960790314],"iteration":314,"passed_time":1.421339411,"remaining_time":3.090849194},
{"learn":[0.04948232667],"iteration":315,"passed_time":1.426935291,"remaining_time":3.088682718},
{"learn":[0.04927333808],"iteration":316,"passed_time":1.431605107,"remaining_time":3.084499332},
{"learn":[0.04911389912],"iteration":317,"passed_time":1.435534574,"remaining_time":3.078725093},
{"learn":[0.04895776073],"iteration":318,"passed_time":1.440156277,"remaining_time":3.074440203},
{"learn":[0.04878678982],"iteration":319,"passed_time":1.444723944,"remaining_time":3.070038381},
{"learn":[0.0485802508],"iteration":320,"passed_time":1.448641991,"remaining_time":3.064261408},
{"learn":[0.04839247465],"iteration":321,"passed_time":1.452658555,"remaining_time":3.058703417},
{"learn":[0.04819176445],"iteration":322,"passed_time":1.458913206,"remaining_time":3.057845947},
{"learn":[0.04804590074],"iteration":323,"passed_time":1.463477468,"remaining_time":3.053428297},
{"learn":[0.04780816297],"iteration":324,"passed_time":1.46745478,"remaining_time":3.047790697},
{"learn":[0.04765120864],"iteration":325,"passed_time":1.473023653,"remaining_time":3.045453809},
{"learn":[0.04748895455],"iteration":326,"passed_time":1.479399491,"remaining_time":3.044757975},
{"learn":[0.04729381618],"iteration":327,"passed_time":1.483796472,"remaining_time":3.039973259},
{"learn":[0.04705576512],"iteration":328,"passed_time":1.48792252,"remaining_time":3.034638332},
{"learn":[0.04688691654],"iteration":329,"passed_time":1.492975324,"remaining_time":3.031192324},
{"learn":[0.04668196881],"iteration":330,"passed_time":1.496905785,"remaining_time":3.025468188},
{"learn":[0.04648070305],"iteration":331,"passed_time":1.500847394,"remaining_time":3.019777288},
{"learn":[0.04623876385],"iteration":332,"passed_time":1.505767822,"remaining_time":3.016057469},
{"learn":[0.04608850197],"iteration":333,"passed_time":1.509872588,"remaining_time":3.010704022},
{"learn":[0.04598583901],"iteration":334,"passed_time":1.514056744,"remaining_time":3.005515626},
{"learn":[0.04582262526],"iteration":335,"passed_time":1.518231776,"remaining_time":3.000315176},
{"learn":[0.04570669144],"iteration":336,"passed_time":1.523483423,"remaining_time":2.997238899},
{"learn":[0.04557817839],"iteration":337,"passed_time":1.52741528,"remaining_time":2.991564837},
{"learn":[0.04543345968],"iteration":338,"passed_time":1.531889022,"remaining_time":2.986957651},
{"learn":[0.04524684914],"iteration":339,"passed_time":1.536351421,"remaining_time":2.98232923},
{"learn":[0.04508492849],"iteration":340,"passed_time":1.541759226,"remaining_time":2.979528827},
{"learn":[0.04495109497],"iteration":341,"passed_time":1.546616215,"remaining_time":2.97565342},
{"learn":[0.04480747427],"iteration":342,"passed_time":1.551237127,"remaining_time":2.971320094},
{"learn":[0.04463313506],"iteration":343,"passed_time":1.556186371,"remaining_time":2.967611219},
{"learn":[0.04438666331],"iteration":344,"passed_time":1.560093992,"remaining_time":2.961917579},
{"learn":[0.04417567793],"iteration":345,"passed_time":1.564141839,"remaining_time":2.956499315},
{"learn":[0.04404996117],"iteration":346,"passed_time":1.568743182,"remaining_time":2.952130541},
{"learn":[0.04392050757],"iteration":347,"passed_time":1.573506233,"remaining_time":2.948063402},
{"learn":[0.04380629616],"iteration":348,"passed_time":1.577520334,"remaining_time":2.942595237},
{"learn":[0.04359775497],"iteration":349,"passed_time":1.58161823,"remaining_time":2.937290998},
{"learn":[0.04336979704],"iteration":350,"passed_time":1.58680566,"remaining_time":2.934008187},
{"learn":[0.04322025802],"iteration":351,"passed_time":1.590816096,"remaining_time":2.928547813},
{"learn":[0.04305686238],"iteration":352,"passed_time":1.595222624,"remaining_time":2.923821636},
{"learn":[0.04288683038],"iteration":353,"passed_time":1.599556516,"remaining_time":2.918964715},
{"learn":[0.04272286614],"iteration":354,"passed_time":1.604179277,"remaining_time":2.914635588},
{"learn":[0.04251181216],"iteration":355,"passed_time":1.608529806,"remaining_time":2.909812345},
{"learn":[0.04236016365],"iteration":356,"passed_time":1.612672491,"remaining_time":2.904617401},
{"learn":[0.04221050059],"iteration":357,"passed_time":1.61822822,"remaining_time":2.901962339},
{"learn":[0.04204982558],"iteration":358,"passed_time":1.62302662,"remaining_time":2.897938894},
{"learn":[0.04195515224],"iteration":359,"passed_time":1.627211775,"remaining_time":2.892820934},
{"learn":[0.04186025432],"iteration":360,"passed_time":1.631247273,"remaining_time":2.887443233},
{"learn":[0.04172705222],"iteration":361,"passed_time":1.636940456,"remaining_time":2.884994505},
{"learn":[0.04157932004],"iteration":362,"passed_time":1.640807693,"remaining_time":2.879323693},
{"learn":[0.0414274563],"iteration":363,"passed_time":1.645432474,"remaining_time":2.87498641},
{"learn":[0.04132261396],"iteration":364,"passed_time":1.650842276,"remaining_time":2.872013274},
{"learn":[0.0411594206],"iteration":365,"passed_time":1.655317536,"remaining_time":2.867407972},
{"learn":[0.04101319211],"iteration":366,"passed_time":1.659113269,"remaining_time":2.861631334},
{"learn":[0.04084365114],"iteration":367,"passed_time":1.663474401,"remaining_time":2.856836472},
{"learn":[0.04073692126],"iteration":368,"passed_time":1.668419695,"remaining_time":2.853042894},
{"learn":[0.04057288464],"iteration":369,"passed_time":1.672836583,"remaining_time":2.84834337},
{"learn":[0.04039417663],"iteration":370,"passed_time":1.677239202,"remaining_time":2.84362118},
{"learn":[0.0402594141],"iteration":371,"passed_time":1.684370843,"remaining_time":2.843507767},
{"learn":[0.04012180866],"iteration":372,"passed_time":1.689001209,"remaining_time":2.839152167},
{"learn":[0.04001010131],"iteration":373,"passed_time":1.692774734,"remaining_time":2.833360919},
{"learn":[0.03988851795],"iteration":374,"passed_time":1.698658897,"remaining_time":2.831098161},
{"learn":[0.03971990949],"iteration":375,"passed_time":1.703279626,"remaining_time":2.826719379},
{"learn":[0.03957553331],"iteration":376,"passed_time":1.707207371,"remaining_time":2.821194143},
{"learn":[0.03947056675],"iteration":377,"passed_time":1.71159221,"remaining_time":2.816429509},
{"learn":[0.03938512079],"iteration":378,"passed_time":1.716094967,"remaining_time":2.811860091},
{"learn":[0.03923555007],"iteration":379,"passed_time":1.720199539,"remaining_time":2.806641353},
{"learn":[0.03912738016],"iteration":380,"passed_time":1.724549334,"remaining_time":2.801826871},
{"learn":[0.03895226831],"iteration":381,"passed_time":1.72945613,"remaining_time":2.797915939},
{"learn":[0.03886383361],"iteration":382,"passed_time":1.734197558,"remaining_time":2.793733403},
{"learn":[0.03870104653],"iteration":383,"passed_time":1.738545668,"remaining_time":2.78891701},
{"learn":[0.03852144987],"iteration":384,"passed_time":1.742985648,"remaining_time":2.784249802},
{"learn":[0.03840495514],"iteration":385,"passed_time":1.747842079,"remaining_time":2.780246209},
{"learn":[0.03821820311],"iteration":386,"passed_time":1.751643108,"remaining_time":2.774566473},
{"learn":[0.03810564732],"iteration":387,"passed_time":1.755756173,"remaining_time":2.769388604},
{"learn":[0.03804723407],"iteration":388,"passed_time":1.761029763,"remaining_time":2.766039037},
{"learn":[0.0379363286],"iteration":389,"passed_time":1.765220109,"remaining_time":2.760985298},
{"learn":[0.03782919835],"iteration":390,"passed_time":1.769015572,"remaining_time":2.75532093},
{"learn":[0.03769350978],"iteration":391,"passed_time":1.77353105,"remaining_time":2.750782854},
{"learn":[0.03754861519],"iteration":392,"passed_time":1.778896138,"remaining_time":2.747557139},
{"learn":[0.03743061904],"iteration":393,"passed_time":1.782719449,"remaining_time":2.741949203},
{"learn":[0.03729491967],"iteration":394,"passed_time":1.786977063,"remaining_time":2.737015502},
{"learn":[0.03721796439],"iteration":395,"passed_time":1.7913929,"remaining_time":2.732326545},
{"learn":[0.0370853126],"iteration":396,"passed_time":1.796082792,"remaining_time":2.728055223},
{"learn":[0.03697448646],"iteration":397,"passed_time":1.800155493,"remaining_time":2.722848258},
{"learn":[0.03685663794],"iteration":398,"passed_time":1.804415014,"remaining_time":2.71792838},
{"learn":[0.03675242094],"iteration":399,"passed_time":1.809884008,"remaining_time":2.714826012},
{"learn":[0.03666505457],"iteration":400,"passed_time":1.814179287,"remaining_time":2.709958585},
{"learn":[0.03652300497],"iteration":401,"passed_time":1.818382837,"remaining_time":2.704957554},
{"learn":[0.03644065484],"iteration":402,"passed_time":1.823652111,"remaining_time":2.701539231},
{"learn":[0.03634864954],"iteration":403,"passed_time":1.829129464,"remaining_time":2.698418714},
{"learn":[0.03627983658],"iteration":404,"passed_time":1.833305065,"remaining_time":2.693374108},
{"learn":[0.03614337189],"iteration":405,"passed_time":1.837676441,"remaining_time":2.688620212},
{"learn":[0.03603922344],"iteration":406,"passed_time":1.843331135,"remaining_time":2.685737993},
{"learn":[0.03590493339],"iteration":407,"passed_time":1.847363469,"remaining_time":2.68048817},
{"learn":[0.0357773722],"iteration":408,"passed_time":1.851167247,"remaining_time":2.674914041},
{"learn":[0.03566128774],"iteration":409,"passed_time":1.855021672,"remaining_time":2.66942143},
{"learn":[0.03555038629],"iteration":410,"passed_time":1.860139136,"remaining_time":2.66574684},
{"learn":[0.03545312584],"iteration":411,"passed_time":1.864396004,"remaining_time":2.660837015},
{"learn":[0.03530738359],"iteration":412,"passed_time":1.868669145,"remaining_time":2.655953482},
{"learn":[0.03515610106],"iteration":413,"passed_time":1.874746767,"remaining_time":2.653627067},
{"learn":[0.03502254591],"iteration":414,"passed_time":1.879008616,"remaining_time":2.648722989},
{"learn":[0.03492001216],"iteration":415,"passed_time":1.882935697,"remaining_time":2.643352036},
{"learn":[0.03479714069],"iteration":416,"passed_time":1.887806696,"remaining_time":2.639307682},
{"learn":[0.03467600033],"iteration":417,"passed_time":1.89377317,"remaining_time":2.636784652},
{"learn":[0.03458914376],"iteration":418,"passed_time":1.898124856,"remaining_time":2.632006065},
{"learn":[0.03448293645],"iteration":419,"passed_time":1.902029048,"remaining_time":2.626611542},
{"learn":[0.03439067619],"iteration":420,"passed_time":1.90797268,"remaining_time":2.624028935},
{"learn":[0.03427684543],"iteration":421,"passed_time":1.912652146,"remaining_time":2.619698911},
{"learn":[0.0341656297],"iteration":422,"passed_time":1.917099192,"remaining_time":2.615050198},
{"learn":[0.03401104736],"iteration":423,"passed_time":1.922804578,"remaining_time":2.61211188},
{"learn":[0.03394950831],"iteration":424,"passed_time":1.928040383,"remaining_time":2.608525224},
{"learn":[0.0338411769],"iteration":425,"passed_time":1.932059746,"remaining_time":2.60329177},
{"learn":[0.03368118149],"iteration":426,"passed_time":1.937480639,"remaining_time":2.599944745},
{"learn":[0.03354117642],"iteration":427,"passed_time":1.941710363,"remaining_time":2.594996092},
{"learn":[0.03345771402],"iteration":428,"passed_time":1.945725309,"remaining_time":2.589764922},
{"learn":[0.03333782107],"iteration":429,"passed_time":1.949822771,"remaining_time":2.584648789},
{"learn":[0.03320802919],"iteration":430,"passed_time":1.956191545,"remaining_time":2.582535937},
{"learn":[0.03311927662],"iteration":431,"passed_time":1.960037402,"remaining_time":2.577086214},
{"learn":[0.03302530849],"iteration":432,"passed_time":1.964321062,"remaining_time":2.572217187},
{"learn":[0.03292865957],"iteration":433,"passed_time":1.969473025,"remaining_time":2.568483254},
{"learn":[0.0328523252],"iteration":434,"passed_time":1.973489116,"remaining_time":2.563267472},
{"learn":[0.03272329819],"iteration":435,"passed_time":1.977618372,"remaining_time":2.558203583},
{"learn":[0.03261906224],"iteration":436,"passed_time":1.981524522,"remaining_time":2.552856535},
{"learn":[0.03251293136],"iteration":437,"passed_time":1.986740394,"remaining_time":2.549196579},
{"learn":[0.03244197597],"iteration":438,"passed_time":1.9910996,"remaining_time":2.544434797},
{"learn":[0.03235081107],"iteration":439,"passed_time":1.995053334,"remaining_time":2.539158788},
{"learn":[0.0322266558],"iteration":440,"passed_time":1.999765892,"remaining_time":2.534850644},
{"learn":[0.03215963108],"iteration":441,"passed_time":2.004194885,"remaining_time":2.530182683},
{"learn":[0.03207774826],"iteration":442,"passed_time":2.008410023,"remaining_time":2.525246914},
{"learn":[0.03199115355],"iteration":443,"passed_time":2.0126439,"remaining_time":2.520337857},
{"learn":[0.03194490195],"iteration":444,"passed_time":2.020249943,"remaining_time":2.519637569},
{"learn":[0.03182280659],"iteration":445,"passed_time":2.026225528,"remaining_time":2.516881037},
{"learn":[0.03173410873],"iteration":446,"passed_time":2.032494013,"remaining_time":2.514472458},
{"learn":[0.03164551557],"iteration":447,"passed_time":2.039774403,"remaining_time":2.513293461},
{"learn":[0.03155648513],"iteration":448,"passed_time":2.045358927,"remaining_time":2.510006167},
{"learn":[0.03145690001],"iteration":449,"passed_time":2.052120977,"remaining_time":2.508147861},
{"learn":[0.03135960324],"iteration":450,"passed_time":2.059395234,"remaining_time":2.506891315},
{"learn":[0.03124805654],"iteration":451,"passed_time":2.066359088,"remaining_time":2.505231814},
{"learn":[0.03115405053],"iteration":452,"passed_time":2.072270746,"remaining_time":2.502278362},
{"learn":[0.03105984438],"iteration":453,"passed_time":2.078599007,"remaining_time":2.499812902},
{"learn":[0.0309890546],"iteration":454,"passed_time":2.090042428,"remaining_time":2.503457413},
{"learn":[0.03085149084],"iteration":455,"passed_time":2.095753097,"remaining_time":2.500196678},
{"learn":[0.03074027026],"iteration":456,"passed_time":2.105215476,"remaining_time":2.501382939},
{"learn":[0.03061585548],"iteration":457,"passed_time":2.110435068,"remaining_time":2.497501761},
{"learn":[0.03055844315],"iteration":458,"passed_time":2.118537483,"remaining_time":2.497012589},
{"learn":[0.03048854977],"iteration":459,"passed_time":2.123756334,"remaining_time":2.493105262},
{"learn":[0.03040407957],"iteration":460,"passed_time":2.12907178,"remaining_time":2.489305183},
{"learn":[0.03033303285],"iteration":461,"passed_time":2.135183604,"remaining_time":2.486425928},
{"learn":[0.030217514],"iteration":462,"passed_time":2.140039539,"remaining_time":2.482076096},
{"learn":[0.0301160473],"iteration":463,"passed_time":2.146318,"remaining_time":2.479367344},
{"learn":[0.03005475697],"iteration":464,"passed_time":2.151139635,"remaining_time":2.474967107},
{"learn":[0.02993850133],"iteration":465,"passed_time":2.155785147,"remaining_time":2.470363237},
{"learn":[0.02984380973],"iteration":466,"passed_time":2.161502524,"remaining_time":2.466982538},
{"learn":[0.02976675293],"iteration":467,"passed_time":2.166763278,"remaining_time":2.463072786},
{"learn":[0.0296685128],"iteration":468,"passed_time":2.171466507,"remaining_time":2.458526045},
{"learn":[0.02955838553],"iteration":469,"passed_time":2.176226624,"remaining_time":2.454042788},
{"learn":[0.02948397589],"iteration":470,"passed_time":2.181588438,"remaining_time":2.450234148},
{"learn":[0.02936281052],"iteration":471,"passed_time":2.186443661,"remaining_time":2.445852231},
{"learn":[0.02931810351],"iteration":472,"passed_time":2.191668917,"remaining_time":2.44188059},
{"learn":[0.02922818748],"iteration":473,"passed_time":2.196330566,"remaining_time":2.437278223},
{"learn":[0.02912536372],"iteration":474,"passed_time":2.200415403,"remaining_time":2.432038077},
{"learn":[0.02904790987],"iteration":475,"passed_time":2.204270834,"remaining_time":2.426550246},
{"learn":[0.02898904199],"iteration":476,"passed_time":2.20999621,"remaining_time":2.423119534},
{"learn":[0.02891076224],"iteration":477,"passed_time":2.214592707,"remaining_time":2.418446429},
{"learn":[0.02883720132],"iteration":478,"passed_time":2.218656563,"remaining_time":2.4131943},
{"learn":[0.02875198599],"iteration":479,"passed_time":2.222894312,"remaining_time":2.408135505},
{"learn":[0.02868780712],"iteration":480,"passed_time":2.22878385,"remaining_time":2.404862408},
{"learn":[0.02858055854],"iteration":481,"passed_time":2.233310075,"remaining_time":2.400113317},
{"learn":[0.02849752959],"iteration":482,"passed_time":2.238589226,"remaining_time":2.396171076},
{"learn":[0.02841236727],"iteration":483,"passed_time":2.244513312,"remaining_time":2.392910887},
{"learn":[0.02832967128],"iteration":484,"passed_time":2.248645945,"remaining_time":2.387737446},
{"learn":[0.02826430866],"iteration":485,"passed_time":2.25325164,"remaining_time":2.383068607},
{"learn":[0.02817161564],"iteration":486,"passed_time":2.260050357,"remaining_time":2.380710129},
{"learn":[0.02808988139],"iteration":487,"passed_time":2.264665494,"remaining_time":2.376042485},
{"learn":[0.02800714983],"iteration":488,"passed_time":2.268598724,"remaining_time":2.37066247},
{"learn":[0.02794612359],"iteration":489,"passed_time":2.274589727,"remaining_time":2.367430124},
{"learn":[0.02784993604],"iteration":490,"passed_time":2.279359504,"remaining_time":2.362920545},
{"learn":[0.02778070612],"iteration":491,"passed_time":2.284220907,"remaining_time":2.358504514},
{"learn":[0.02765132014],"iteration":492,"passed_time":2.291913102,"remaining_time":2.356997855},
{"learn":[0.02758118358],"iteration":493,"passed_time":2.296546347,"remaining_time":2.352332898},
{"learn":[0.02750506119],"iteration":494,"passed_time":2.300675241,"remaining_time":2.347153529},
{"learn":[0.02745068574],"iteration":495,"passed_time":2.312285315,"remaining_time":2.34958024},
{"learn":[0.0273628006],"iteration":496,"passed_time":2.316917254,"remaining_time":2.344888086},
{"learn":[0.02728055633],"iteration":497,"passed_time":2.322031039,"remaining_time":2.34068189},
{"learn":[0.02722276432],"iteration":498,"passed_time":2.327111353,"remaining_time":2.336438452},
{"learn":[0.02711527197],"iteration":499,"passed_time":2.331396239,"remaining_time":2.331396239},
{"learn":[0.02702709591],"iteration":500,"passed_time":2.335708282,"remaining_time":2.326384097},
{"learn":[0.02693323543],"iteration":501,"passed_time":2.341020148,"remaining_time":2.322366601},
{"learn":[0.02685101801],"iteration":502,"passed_time":2.344818619,"remaining_time":2.316848615},
{"learn":[0.02676179155],"iteration":503,"passed_time":2.348998592,"remaining_time":2.3117129},
{"learn":[0.02668250991],"iteration":504,"passed_time":2.354115264,"remaining_time":2.30749912},
{"learn":[0.02663736379],"iteration":505,"passed_time":2.358195995,"remaining_time":2.302270398},
{"learn":[0.02658113688],"iteration":506,"passed_time":2.362602311,"remaining_time":2.297362799},
{"learn":[0.02654325103],"iteration":507,"passed_time":2.366508198,"remaining_time":2.291972507},
{"learn":[0.02646092775],"iteration":508,"passed_time":2.372919427,"remaining_time":2.289004791},
{"learn":[0.0263501048],"iteration":509,"passed_time":2.377087274,"remaining_time":2.283868165},
{"learn":[0.02629507162],"iteration":510,"passed_time":2.380933548,"remaining_time":2.278427603},
{"learn":[0.02622058288],"iteration":511,"passed_time":2.38655245,"remaining_time":2.274682804},
{"learn":[0.02617413209],"iteration":512,"passed_time":2.390857698,"remaining_time":2.269683624},
{"learn":[0.02610217502],"iteration":513,"passed_time":2.394621447,"remaining_time":2.264175142},
{"learn":[0.02604464143],"iteration":514,"passed_time":2.398796508,"remaining_time":2.259060789},
{"learn":[0.02596200173],"iteration":515,"passed_time":2.403913113,"remaining_time":2.25483323},
{"learn":[0.02589088304],"iteration":516,"passed_time":2.408434065,"remaining_time":2.250045751},
{"learn":[0.02582633748],"iteration":517,"passed_time":2.412878877,"remaining_time":2.245188453},
{"learn":[0.025770217],"iteration":518,"passed_time":2.417487464,"remaining_time":2.240484528},
{"learn":[0.02568692888],"iteration":519,"passed_time":2.421588189,"remaining_time":2.235312174},
{"learn":[0.02560217266],"iteration":520,"passed_time":2.425379899,"remaining_time":2.22985983},
{"learn":[0.02553658011],"iteration":521,"passed_time":2.429582415,"remaining_time":2.224790028},
{"learn":[0.02546531626],"iteration":522,"passed_time":2.435843171,"remaining_time":2.221600751},
{"learn":[0.02542485361],"iteration":523,"passed_time":2.440513302,"remaining_time":2.216954832},
{"learn":[0.02534627034],"iteration":524,"passed_time":2.444784953,"remaining_time":2.211948291},
{"learn":[0.02527097895],"iteration":525,"passed_time":2.450064075,"remaining_time":2.207852418},
{"learn":[0.0252052245],"iteration":526,"passed_time":2.454311329,"remaining_time":2.202825918},
{"learn":[0.02512804412],"iteration":527,"passed_time":2.458235087,"remaining_time":2.197513183},
{"learn":[0.0250499553],"iteration":528,"passed_time":2.462574976,"remaining_time":2.192576207},
{"learn":[0.02500630914],"iteration":529,"passed_time":2.468031491,"remaining_time":2.188631699},
{"learn":[0.02496965223],"iteration":530,"passed_time":2.472394942,"remaining_time":2.18371606},
{"learn":[0.02487572098],"iteration":531,"passed_time":2.476263955,"remaining_time":2.178367539},
{"learn":[0.02481652043],"iteration":532,"passed_time":2.481497712,"remaining_time":2.174220322},
{"learn":[0.02476449212],"iteration":533,"passed_time":2.485511507,"remaining_time":2.169004423},
{"learn":[0.02469358728],"iteration":534,"passed_time":2.489786386,"remaining_time":2.164019943},
{"learn":[0.02463477531],"iteration":535,"passed_time":2.494196748,"remaining_time":2.159155394},
{"learn":[0.02459905576],"iteration":536,"passed_time":2.499858318,"remaining_time":2.155371324},
{"learn":[0.02453984227],"iteration":537,"passed_time":2.504114919,"remaining_time":2.150373778},
{"learn":[0.02446650173],"iteration":538,"passed_time":2.508084638,"remaining_time":2.145133615},
{"learn":[0.0243788125],"iteration":539,"passed_time":2.515943786,"remaining_time":2.143211373},
{"learn":[0.02430058104],"iteration":540,"passed_time":2.520438024,"remaining_time":2.138412298},
{"learn":[0.02424978284],"iteration":541,"passed_time":2.525206338,"remaining_time":2.133845946},
{"learn":[0.0241898395],"iteration":542,"passed_time":2.532027117,"remaining_time":2.131006247},
{"learn":[0.02412558252],"iteration":543,"passed_time":2.536837011,"remaining_time":2.126466318},
{"learn":[0.02406166049],"iteration":544,"passed_time":2.540722248,"remaining_time":2.121153437},
{"learn":[0.02400988389],"iteration":545,"passed_time":2.546199293,"remaining_time":2.117169375},
{"learn":[0.0239437541],"iteration":546,"passed_time":2.550353131,"remaining_time":2.112084037},
{"learn":[0.02388556409],"iteration":547,"passed_time":2.554209221,"remaining_time":2.106756511},
{"learn":[0.02383463311],"iteration":548,"passed_time":2.559249187,"remaining_time":2.102406892},
{"learn":[0.02377900242],"iteration":549,"passed_time":2.564066185,"remaining_time":2.097872333},
{"learn":[0.02369915503],"iteration":550,"passed_time":2.568285788,"remaining_time":2.092849943},
{"learn":[0.02366957447],"iteration":551,"passed_time":2.572440699,"remaining_time":2.087777958},
{"learn":[0.0236132861],"iteration":552,"passed_time":2.577385119,"remaining_time":2.083347465},
{"learn":[0.02351990698],"iteration":553,"passed_time":2.581788848,"remaining_time":2.078479831},
{"learn":[0.02345679249],"iteration":554,"passed_time":2.585708352,"remaining_time":2.073225616},
{"learn":[0.02339407062],"iteration":555,"passed_time":2.590177529,"remaining_time":2.068415149},
{"learn":[0.02333867751],"iteration":556,"passed_time":2.595391542,"remaining_time":2.0641983},
{"learn":[0.0232904366],"iteration":557,"passed_time":2.599727989,"remaining_time":2.059282744},
{"learn":[0.02324195677],"iteration":558,"passed_time":2.604469231,"remaining_time":2.054688606},
{"learn":[0.0231742547],"iteration":559,"passed_time":2.610204607,"remaining_time":2.050875048},
{"learn":[0.02313715679],"iteration":560,"passed_time":2.614154721,"remaining_time":2.045657616},
{"learn":[0.02308528552],"iteration":561,"passed_time":2.61866869,"remaining_time":2.040884139},
{"learn":[0.02302316929],"iteration":562,"passed_time":2.623464221,"remaining_time":2.036330132},
{"learn":[0.02296085487],"iteration":563,"passed_time":2.628995948,"remaining_time":2.032344385},
{"learn":[0.02292901684],"iteration":564,"passed_time":2.633429242,"remaining_time":2.027507469},
{"learn":[0.02284971968],"iteration":565,"passed_time":2.637972148,"remaining_time":2.022756028},
{"learn":[0.02277961277],"iteration":566,"passed_time":2.644495051,"remaining_time":2.019517385},
{"learn":[0.02273240239],"iteration":567,"passed_time":2.649044498,"remaining_time":2.014766238},
{"learn":[0.02267719478],"iteration":568,"passed_time":2.652967976,"remaining_time":2.009541648},
{"learn":[0.02261721818],"iteration":569,"passed_time":2.660357379,"remaining_time":2.006936269},
{"learn":[0.02255024298],"iteration":570,"passed_time":2.66584139,"remaining_time":2.002882586},
{"learn":[0.02247056898],"iteration":571,"passed_time":2.670157591,"remaining_time":1.997950086},
{"learn":[0.02240631206],"iteration":572,"passed_time":2.676068019,"remaining_time":1.994207756},
{"learn":[0.0223542206],"iteration":573,"passed_time":2.680973384,"remaining_time":1.989711954},
{"learn":[0.0222568559],"iteration":574,"passed_time":2.685473752,"remaining_time":1.984915382},
{"learn":[0.02221106536],"iteration":575,"passed_time":2.692930464,"remaining_time":1.982296036},
{"learn":[0.02215483694],"iteration":576,"passed_time":2.698155225,"remaining_time":1.978023675},
{"learn":[0.02208288352],"iteration":577,"passed_time":2.701992342,"remaining_time":1.972734893},
{"learn":[0.02203146896],"iteration":578,"passed_time":2.708568459,"remaining_time":1.969442696},
{"learn":[0.02197264777],"iteration":579,"passed_time":2.713750853,"remaining_time":1.965129928},
{"learn":[0.02192456744],"iteration":580,"passed_time":2.731634253,"remaining_time":1.969973756},
{"learn":[0.02181791884],"iteration":581,"passed_time":2.742746031,"remaining_time":1.969876015},
{"learn":[0.02177425659],"iteration":582,"passed_time":2.746681341,"remaining_time":1.964607408},
{"learn":[0.02168909447],"iteration":583,"passed_time":2.750524104,"remaining_time":1.959277444},
{"learn":[0.02163063349],"iteration":584,"passed_time":2.756540014,"remaining_time":1.955494198},
{"learn":[0.02158284912],"iteration":585,"passed_time":2.760576807,"remaining_time":1.950305116},
{"learn":[0.02152245197],"iteration":586,"passed_time":2.764369064,"remaining_time":1.944947911},
{"learn":[0.02147208675],"iteration":587,"passed_time":2.768214933,"remaining_time":1.939633592},
{"learn":[0.0214044495],"iteration":588,"passed_time":2.772996817,"remaining_time":1.934977405},
{"learn":[0.02132680026],"iteration":589,"passed_time":2.776771367,"remaining_time":1.929620781},
{"learn":[0.02129249493],"iteration":590,"passed_time":2.780477669,"remaining_time":1.924222279},
{"learn":[0.02122016852],"iteration":591,"passed_time":2.785298055,"remaining_time":1.919597308},
{"learn":[0.02116079317],"iteration":592,"passed_time":2.790318626,"remaining_time":1.915109074},
{"learn":[0.02112326656],"iteration":593,"passed_time":2.794754836,"remaining_time":1.910219636},
{"learn":[0.02108640056],"iteration":594,"passed_time":2.800379362,"remaining_time":1.906140574},
{"learn":[0.02102661915],"iteration":595,"passed_time":2.805260793,"remaining_time":1.901552618},
{"learn":[0.02099142428],"iteration":596,"passed_time":2.80931632,"remaining_time":1.896406159},
{"learn":[0.02095246981],"iteration":597,"passed_time":2.813228978,"remaining_time":1.891167307},
{"learn":[0.02091121097],"iteration":598,"passed_time":2.817728101,"remaining_time":1.88632549},
{"learn":[0.02086424959],"iteration":599,"passed_time":2.821674431,"remaining_time":1.881116287},
{"learn":[0.02081270353],"iteration":600,"passed_time":2.825433679,"remaining_time":1.875787085},
{"learn":[0.02075582232],"iteration":601,"passed_time":2.82919509,"remaining_time":1.870464528},
{"learn":[0.02071844588],"iteration":602,"passed_time":2.83455953,"remaining_time":1.866202543},
{"learn":[0.02068449871],"iteration":603,"passed_time":2.839259455,"remaining_time":1.861501232},
{"learn":[0.02061951975],"iteration":604,"passed_time":2.843056573,"remaining_time":1.85621049},
{"learn":[0.02057719898],"iteration":605,"passed_time":2.846832765,"remaining_time":1.850911072},
{"learn":[0.02051395933],"iteration":606,"passed_time":2.851923996,"remaining_time":1.84646809},
{"learn":[0.02044906337],"iteration":607,"passed_time":2.855672736,"remaining_time":1.841157422},
{"learn":[0.02038726689],"iteration":608,"passed_time":2.859404584,"remaining_time":1.835841039},
{"learn":[0.02033564006],"iteration":609,"passed_time":2.863171609,"remaining_time":1.83055234},
{"learn":[0.02026710363],"iteration":610,"passed_time":2.868134231,"remaining_time":1.826029813},
{"learn":[0.02018628656],"iteration":611,"passed_time":2.871835501,"remaining_time":1.820706167},
{"learn":[0.0201169065],"iteration":612,"passed_time":2.875589264,"remaining_time":1.815420955},
{"learn":[0.02006731213],"iteration":613,"passed_time":2.879359666,"remaining_time":1.810151191},
{"learn":[0.02002721553],"iteration":614,"passed_time":2.884194049,"remaining_time":1.805552372},
{"learn":[0.01999641661],"iteration":615,"passed_time":2.888144316,"remaining_time":1.800401652},
{"learn":[0.01993720512],"iteration":616,"passed_time":2.891873837,"remaining_time":1.795117795},
{"learn":[0.01986469481],"iteration":617,"passed_time":2.89630563,"remaining_time":1.790273059},
{"learn":[0.01981929376],"iteration":618,"passed_time":2.901477019,"remaining_time":1.785884886},
{"learn":[0.01976796982],"iteration":619,"passed_time":2.905215473,"remaining_time":1.780615935},
{"learn":[0.01973495937],"iteration":620,"passed_time":2.9090683,"remaining_time":1.775421716},
{"learn":[0.01966758359],"iteration":621,"passed_time":2.915445414,"remaining_time":1.771765863},
{"learn":[0.01961925142],"iteration":622,"passed_time":2.919964282,"remaining_time":1.766976781},
{"learn":[0.01956053421],"iteration":623,"passed_time":2.923788474,"remaining_time":1.761769978},
{"learn":[0.01951314528],"iteration":624,"passed_time":2.928947028,"remaining_time":1.757368217},
{"learn":[0.01948407563],"iteration":625,"passed_time":2.933964595,"remaining_time":1.752879806},
{"learn":[0.01944466051],"iteration":626,"passed_time":2.938080746,"remaining_time":1.747853458},
{"learn":[0.01939702679],"iteration":627,"passed_time":2.941761865,"remaining_time":1.742572315},
{"learn":[0.01934064212],"iteration":628,"passed_time":2.946928543,"remaining_time":1.738172479},
{"learn":[0.01930145457],"iteration":629,"passed_time":2.950804272,"remaining_time":1.733012033},
{"learn":[0.0192555859],"iteration":630,"passed_time":2.956016494,"remaining_time":1.72863722},
{"learn":[0.01921238616],"iteration":631,"passed_time":2.960127636,"remaining_time":1.723618623},
{"learn":[0.0191573399],"iteration":632,"passed_time":2.965649077,"remaining_time":1.719420555},
{"learn":[0.01911045092],"iteration":633,"passed_time":2.969826994,"remaining_time":1.714442713},
{"learn":[0.01908089905],"iteration":634,"passed_time":2.974171978,"remaining_time":1.70956342},
{"learn":[0.01904669147],"iteration":635,"passed_time":2.979389343,"remaining_time":1.705185096},
{"learn":[0.01899623354],"iteration":636,"passed_time":2.983183247,"remaining_time":1.699992965},
{"learn":[0.01892898427],"iteration":637,"passed_time":2.986996432,"remaining_time":1.694816158},
{"learn":[0.01886935354],"iteration":638,"passed_time":2.990731351,"remaining_time":1.689599402},
{"learn":[0.01882895872],"iteration":639,"passed_time":2.996044041,"remaining_time":1.685274773},
{"learn":[0.0187915292],"iteration":640,"passed_time":2.999946088,"remaining_time":1.680157013},
{"learn":[0.01873874998],"iteration":641,"passed_time":3.003766478,"remaining_time":1.674997507},
{"learn":[0.01869666861],"iteration":642,"passed_time":3.007492266,"remaining_time":1.66978964},
{"learn":[0.01864756433],"iteration":643,"passed_time":3.012469651,"remaining_time":1.665278254},
{"learn":[0.01858771478],"iteration":644,"passed_time":3.016732628,"remaining_time":1.660372222},
{"learn":[0.01854220335],"iteration":645,"passed_time":3.020615689,"remaining_time":1.655259991},
{"learn":[0.01850294845],"iteration":646,"passed_time":3.024547115,"remaining_time":1.650177947},
{"learn":[0.01847035905],"iteration":647,"passed_time":3.029145618,"remaining_time":1.645461817},
{"learn":[0.01845572452],"iteration":648,"passed_time":3.033018149,"remaining_time":1.640353421},
{"learn":[0.0184079973],"iteration":649,"passed_time":3.036784345,"remaining_time":1.63519157},
{"learn":[0.01834944081],"iteration":650,"passed_time":3.040637608,"remaining_time":1.630080684},
{"learn":[0.01830244944],"iteration":651,"passed_time":3.045988595,"remaining_time":1.625773054},
{"learn":[0.01826331455],"iteration":652,"passed_time":3.050106822,"remaining_time":1.620807148},
{"learn":[0.01820738004],"iteration":653,"passed_time":3.053793502,"remaining_time":1.615615523},
{"learn":[0.01816810277],"iteration":654,"passed_time":3.059115647,"remaining_time":1.611289921},
{"learn":[0.01814976346],"iteration":655,"passed_time":3.063015635,"remaining_time":1.606215516},
{"learn":[0.01813508822],"iteration":656,"passed_time":3.06560686,"remaining_time":1.60046142},
{"learn":[0.01809845336],"iteration":657,"passed_time":3.069362563,"remaining_time":1.595322183},
{"learn":[0.01804561082],"iteration":658,"passed_time":3.07673971,"remaining_time":1.592061064},
{"learn":[0.01802313533],"iteration":659,"passed_time":3.081288698,"remaining_time":1.587330541},
{"learn":[0.01797170678],"iteration":660,"passed_time":3.085151367,"remaining_time":1.582248583},
{"learn":[0.01794299164],"iteration":661,"passed_time":3.089559145,"remaining_time":1.577448627},
{"learn":[0.01790037056],"iteration":662,"passed_time":3.094112238,"remaining_time":1.572723717},
{"learn":[0.01785158802],"iteration":663,"passed_time":3.097828996,"remaining_time":1.567576119},
{"learn":[0.0178144284],"iteration":664,"passed_time":3.101642375,"remaining_time":1.562481497},
{"learn":[0.01776318242],"iteration":665,"passed_time":3.108096214,"remaining_time":1.558714918},
{"learn":[0.01772673269],"iteration":666,"passed_time":3.112366913,"remaining_time":1.553850348},
{"learn":[0.0176896579],"iteration":667,"passed_time":3.116083714,"remaining_time":1.548712265},
{"learn":[0.0176508615],"iteration":668,"passed_time":3.121237446,"remaining_time":1.544289379},
{"learn":[0.01760231718],"iteration":669,"passed_time":3.127675824,"remaining_time":1.540497048},
{"learn":[0.01756696833],"iteration":670,"passed_time":3.132236742,"remaining_time":1.535776286},
{"learn":[0.01752210168],"iteration":671,"passed_time":3.13656392,"remaining_time":1.530941913},
{"learn":[0.0174674575],"iteration":672,"passed_time":3.141301416,"remaining_time":1.526308415},
{"learn":[0.0174241684],"iteration":673,"passed_time":3.145019643,"remaining_time":1.521181608},
{"learn":[0.01739647009],"iteration":674,"passed_time":3.148708491,"remaining_time":1.516044829},
{"learn":[0.01736754751],"iteration":675,"passed_time":3.152666462,"remaining_time":1.511041322},
{"learn":[0.01729803917],"iteration":676,"passed_time":3.157579884,"remaining_time":1.506496754},
{"learn":[0.0172594292],"iteration":677,"passed_time":3.161279545,"remaining_time":1.501374651},
{"learn":[0.0172195995],"iteration":678,"passed_time":3.164996651,"remaining_time":1.496264985},
{"learn":[0.01717858689],"iteration":679,"passed_time":3.169066482,"remaining_time":1.491325403},
{"learn":[0.01713553233],"iteration":680,"passed_time":3.173582926,"remaining_time":1.486597582},
{"learn":[0.01709341513],"iteration":681,"passed_time":3.177370976,"remaining_time":1.481530748},
{"learn":[0.01706341486],"iteration":682,"passed_time":3.181074623,"remaining_time":1.476428485},
{"learn":[0.01702137492],"iteration":683,"passed_time":3.18541542,"remaining_time":1.471624668},
{"learn":[0.0169829572],"iteration":684,"passed_time":3.189856691,"remaining_time":1.466868405},
{"learn":[0.0169378981],"iteration":685,"passed_time":3.19372179,"remaining_time":1.461849333},
{"learn":[0.01687662959],"iteration":686,"passed_time":3.197868777,"remaining_time":1.456962048},
{"learn":[0.01683332087],"iteration":687,"passed_time":3.203046922,"remaining_time":1.452544534},
{"learn":[0.01678951113],"iteration":688,"passed_time":3.208405475,"remaining_time":1.448206245},
{"learn":[0.01674535532],"iteration":689,"passed_time":3.212618534,"remaining_time":1.443350356},
{"learn":[0.01671172631],"iteration":690,"passed_time":3.216481816,"remaining_time":1.438339915},
{"learn":[0.0166752155],"iteration":691,"passed_time":3.222094577,"remaining_time":1.434111459},
{"learn":[0.01663729441],"iteration":692,"passed_time":3.22698649,"remaining_time":1.429559672},
{"learn":[0.01659761873],"iteration":693,"passed_time":3.230900924,"remaining_time":1.424575912},
{"learn":[0.01653583199],"iteration":694,"passed_time":3.237330308,"remaining_time":1.420698912},
{"learn":[0.0165084192],"iteration":695,"passed_time":3.242584842,"remaining_time":1.416301425},
{"learn":[0.01647028879],"iteration":696,"passed_time":3.246418692,"remaining_time":1.411283879},
{"learn":[0.01643479258],"iteration":697,"passed_time":3.252460623,"remaining_time":1.407225083},
{"learn":[0.01639046739],"iteration":698,"passed_time":3.257283425,"remaining_time":1.402635638},
{"learn":[0.01634469599],"iteration":699,"passed_time":3.261816989,"remaining_time":1.397921567},
{"learn":[0.01629543188],"iteration":700,"passed_time":3.267092266,"remaining_time":1.393524376},
{"learn":[0.01626197438],"iteration":701,"passed_time":3.271843384,"remaining_time":1.388902177},
{"learn":[0.01623265772],"iteration":702,"passed_time":3.276162105,"remaining_time":1.384096935},
{"learn":[0.01619385114],"iteration":703,"passed_time":3.279939441,"remaining_time":1.379065447},
{"learn":[0.0161484474],"iteration":704,"passed_time":3.285633634,"remaining_time":1.374839606},
{"learn":[0.01610498035],"iteration":705,"passed_time":3.290068629,"remaining_time":1.370085236},
{"learn":[0.01606754708],"iteration":706,"passed_time":3.293817622,"remaining_time":1.365047473},
{"learn":[0.01603739136],"iteration":707,"passed_time":3.300784798,"remaining_time":1.361340623},
{"learn":[0.01600638865],"iteration":708,"passed_time":3.306204531,"remaining_time":1.356989448},
{"learn":[0.01595612064],"iteration":709,"passed_time":3.31090161,"remaining_time":1.352340094},
{"learn":[0.01591884166],"iteration":710,"passed_time":3.318943444,"remaining_time":1.349050148},
{"learn":[0.0158935577],"iteration":711,"passed_time":3.323598832,"remaining_time":1.344377056},
{"learn":[0.01585760583],"iteration":712,"passed_time":3.328037378,"remaining_time":1.339616729},
{"learn":[0.01581816005],"iteration":713,"passed_time":3.335150635,"remaining_time":1.335928686},
{"learn":[0.0157923975],"iteration":714,"passed_time":3.340281067,"remaining_time":1.331440705},
{"learn":[0.01575739151],"iteration":715,"passed_time":3.345830846,"remaining_time":1.327117263},
{"learn":[0.01572744414],"iteration":716,"passed_time":3.35154141,"remaining_time":1.322853862},
{"learn":[0.01570053845],"iteration":717,"passed_time":3.356233259,"remaining_time":1.318186322},
{"learn":[0.01565827553],"iteration":718,"passed_time":3.361345666,"remaining_time":1.313683077},
{"learn":[0.01563671906],"iteration":719,"passed_time":3.367604682,"remaining_time":1.309624043},
{"learn":[0.01559912888],"iteration":720,"passed_time":3.372234033,"remaining_time":1.304928288},
{"learn":[0.01557048157],"iteration":721,"passed_time":3.377264696,"remaining_time":1.300387237},
{"learn":[0.01553865986],"iteration":722,"passed_time":3.383066119,"remaining_time":1.296140131},
{"learn":[0.01551596479],"iteration":723,"passed_time":3.387687491,"remaining_time":1.291438878},
{"learn":[0.01547385794],"iteration":724,"passed_time":3.392106622,"remaining_time":1.286661133},
{"learn":[0.01542993223],"iteration":725,"passed_time":3.397786982,"remaining_time":1.282360376},
{"learn":[0.01538736101],"iteration":726,"passed_time":3.402009153,"remaining_time":1.277508251},
{"learn":[0.01536050124],"iteration":727,"passed_time":3.405832083,"remaining_time":1.27250869},
{"learn":[0.01531901465],"iteration":728,"passed_time":3.410663636,"remaining_time":1.267887305},
{"learn":[0.01527891807],"iteration":729,"passed_time":3.414945987,"remaining_time":1.263062214},
{"learn":[0.01523847664],"iteration":730,"passed_time":3.418909835,"remaining_time":1.258121403},
{"learn":[0.01522111599],"iteration":731,"passed_time":3.423126295,"remaining_time":1.253275747},
{"learn":[0.01517947836],"iteration":732,"passed_time":3.428750864,"remaining_time":1.248944721},
{"learn":[0.0151486071],"iteration":733,"passed_time":3.433321647,"remaining_time":1.244228281},
{"learn":[0.01510888896],"iteration":734,"passed_time":3.437474703,"remaining_time":1.239361628},
{"learn":[0.01507585395],"iteration":735,"passed_time":3.442058324,"remaining_time":1.234651355},
{"learn":[0.01504672863],"iteration":736,"passed_time":3.446603561,"remaining_time":1.229927729},
{"learn":[0.01502062143],"iteration":737,"passed_time":3.451013072,"remaining_time":1.225156402},
{"learn":[0.01499544979],"iteration":738,"passed_time":3.454830793,"remaining_time":1.220177046},
{"learn":[0.01497543196],"iteration":739,"passed_time":3.460970269,"remaining_time":1.216016581},
{"learn":[0.01495612284],"iteration":740,"passed_time":3.464975425,"remaining_time":1.211104771},
{"learn":[0.01493078765],"iteration":741,"passed_time":3.468736331,"remaining_time":1.206110476},
{"learn":[0.01488858418],"iteration":742,"passed_time":3.474101712,"remaining_time":1.201674482},
{"learn":[0.01486353905],"iteration":743,"passed_time":3.478163959,"remaining_time":1.196787599},
{"learn":[0.01483904117],"iteration":744,"passed_time":3.481859776,"remaining_time":1.191777507},
{"learn":[0.0148132839],"iteration":745,"passed_time":3.485686133,"remaining_time":1.186815386},
{"learn":[0.0147958691],"iteration":746,"passed_time":3.490568625,"remaining_time":1.182214005},
{"learn":[0.01476952653],"iteration":747,"passed_time":3.494314039,"remaining_time":1.177228794},
{"learn":[0.01474429062],"iteration":748,"passed_time":3.498784466,"remaining_time":1.172489855},
{"learn":[0.01470171965],"iteration":749,"passed_time":3.503023554,"remaining_time":1.167674518},
{"learn":[0.0146805962],"iteration":750,"passed_time":3.507712993,"remaining_time":1.163010034},
{"learn":[0.01464051709],"iteration":751,"passed_time":3.51139857,"remaining_time":1.158014422},
{"learn":[0.01461601475],"iteration":752,"passed_time":3.516198859,"remaining_time":1.153387939},
{"learn":[0.01458897561],"iteration":753,"passed_time":3.520442877,"remaining_time":1.148579506},
{"learn":[0.0145561881],"iteration":754,"passed_time":3.526470577,"remaining_time":1.144351379},
{"learn":[0.01452943713],"iteration":755,"passed_time":3.530794774,"remaining_time":1.139568684},
{"learn":[0.01450399926],"iteration":756,"passed_time":3.534475446,"remaining_time":1.134580625},
{"learn":[0.01446882823],"iteration":757,"passed_time":3.539404358,"remaining_time":1.129994531},
{"learn":[0.01443602052],"iteration":758,"passed_time":3.543117124,"remaining_time":1.125021379},
{"learn":[0.01441793517],"iteration":759,"passed_time":3.546797863,"remaining_time":1.120041431},
{"learn":[0.01440776778],"iteration":760,"passed_time":3.550539291,"remaining_time":1.115083956},
{"learn":[0.01437898971],"iteration":761,"passed_time":3.555608092,"remaining_time":1.11054426},
{"learn":[0.01434701618],"iteration":762,"passed_time":3.559332741,"remaining_time":1.105585661},
{"learn":[0.01431627077],"iteration":763,"passed_time":3.562943431,"remaining_time":1.100595091},
{"learn":[0.01427035839],"iteration":764,"passed_time":3.566724733,"remaining_time":1.095660539},
{"learn":[0.01423402013],"iteration":765,"passed_time":3.571551053,"remaining_time":1.091048233},
{"learn":[0.014194306],"iteration":766,"passed_time":3.57525498,"remaining_time":1.086094407},
{"learn":[0.01416964496],"iteration":767,"passed_time":3.578875287,"remaining_time":1.081118576},
{"learn":[0.01413597336],"iteration":768,"passed_time":3.582651987,"remaining_time":1.07619325},
{"learn":[0.01410527043],"iteration":769,"passed_time":3.587532964,"remaining_time":1.071600756},
{"learn":[0.01407867163],"iteration":770,"passed_time":3.591258374,"remaining_time":1.06666429},
{"learn":[0.01404911026],"iteration":771,"passed_time":3.594958454,"remaining_time":1.061723481},
{"learn":[0.01400518434],"iteration":772,"passed_time":3.600391648,"remaining_time":1.057294831},
{"learn":[0.01398320345],"iteration":773,"passed_time":3.605214226,"remaining_time":1.052685291},
{"learn":[0.01396051386],"iteration":774,"passed_time":3.609042104,"remaining_time":1.047786417},
{"learn":[0.01392338318],"iteration":775,"passed_time":3.612998981,"remaining_time":1.042927541},
{"learn":[0.01389334724],"iteration":776,"passed_time":3.617198201,"remaining_time":1.038140539},
{"learn":[0.01386348851],"iteration":777,"passed_time":3.622121963,"remaining_time":1.033561794},
{"learn":[0.01383264563],"iteration":778,"passed_time":3.625946427,"remaining_time":1.028670296},
{"learn":[0.01379959655],"iteration":779,"passed_time":3.629652068,"remaining_time":1.023748019},
{"learn":[0.01376170554],"iteration":780,"passed_time":3.634758759,"remaining_time":1.019221726},
{"learn":[0.01374682091],"iteration":781,"passed_time":3.63856997,"remaining_time":1.014332805},
{"learn":[0.01371416927],"iteration":782,"passed_time":3.642218566,"remaining_time":1.009401569},
{"learn":[0.01370104755],"iteration":783,"passed_time":3.645948859,"remaining_time":1.004496114},
{"learn":[0.01367438558],"iteration":784,"passed_time":3.65093106,"remaining_time":0.9999365323},
{"learn":[0.01365305069],"iteration":785,"passed_time":3.654736326,"remaining_time":0.9950554374},
{"learn":[0.01362058172],"iteration":786,"passed_time":3.658423893,"remaining_time":0.9901452213},
{"learn":[0.01359533438],"iteration":787,"passed_time":3.662077673,"remaining_time":0.9852290186},
{"learn":[0.01357900132],"iteration":788,"passed_time":3.667123451,"remaining_time":0.9806882739},
{"learn":[0.01354880759],"iteration":789,"passed_time":3.671418069,"remaining_time":0.9759465752},
{"learn":[0.01353145146],"iteration":790,"passed_time":3.675674181,"remaining_time":0.971195833},
{"learn":[0.01351452657],"iteration":791,"passed_time":3.679366693,"remaining_time":0.9662983235},
{"learn":[0.0134888982],"iteration":792,"passed_time":3.684011173,"remaining_time":0.961652349},
{"learn":[0.01346448227],"iteration":793,"passed_time":3.687659605,"remaining_time":0.956747958},
{"learn":[0.0134371307],"iteration":794,"passed_time":3.691331113,"remaining_time":0.9518526769},
{"learn":[0.01340893935],"iteration":795,"passed_time":3.69494376,"remaining_time":0.9469453856},
{"learn":[0.01336717301],"iteration":796,"passed_time":3.700868786,"remaining_time":0.942630318},
{"learn":[0.01334520539],"iteration":797,"passed_time":3.704816877,"remaining_time":0.9378107884},
{"learn":[0.0133179667],"iteration":798,"passed_time":3.708532317,"remaining_time":0.9329349134},
{"learn":[0.01328516401],"iteration":799,"passed_time":3.71288216,"remaining_time":0.9282205401},
{"learn":[0.01324612709],"iteration":800,"passed_time":3.718639114,"remaining_time":0.9238566588},
{"learn":[0.01323002372],"iteration":801,"passed_time":3.722693928,"remaining_time":0.9190690746},
{"learn":[0.01319568864],"iteration":802,"passed_time":3.726314658,"remaining_time":0.9141768214},
{"learn":[0.01315977783],"iteration":803,"passed_time":3.732150542,"remaining_time":0.9098277441},
{"learn":[0.01313298172],"iteration":804,"passed_time":3.737507266,"remaining_time":0.905358903},
{"learn":[0.01310015343],"iteration":805,"passed_time":3.741864489,"remaining_time":0.900647284},
{"learn":[0.01306296108],"iteration":806,"passed_time":3.747432071,"remaining_time":0.8962260096},
{"learn":[0.01303803457],"iteration":807,"passed_time":3.751856029,"remaining_time":0.8915301455},
{"learn":[0.0130236735],"iteration":808,"passed_time":3.756318805,"remaining_time":0.8868441183},
{"learn":[0.01300767639],"iteration":809,"passed_time":3.761403991,"remaining_time":0.8823046398},
{"learn":[0.01297114005],"iteration":810,"passed_time":3.766060285,"remaining_time":0.8776638641},
{"learn":[0.01294821252],"iteration":811,"passed_time":3.770493698,"remaining_time":0.8729714473},
{"learn":[0.01291891555],"iteration":812,"passed_time":3.77462049,"remaining_time":0.868209141},
{"learn":[0.01289405874],"iteration":813,"passed_time":3.779582211,"remaining_time":0.8636391784},
{"learn":[0.01285727597],"iteration":814,"passed_time":3.783961102,"remaining_time":0.8589359557},
{"learn":[0.01281856514],"iteration":815,"passed_time":3.78811755,"remaining_time":0.8541833692},
{"learn":[0.01278851736],"iteration":816,"passed_time":3.793056039,"remaining_time":0.8496074115},
{"learn":[0.01276953703],"iteration":817,"passed_time":3.79740805,"remaining_time":0.8449000797},
{"learn":[0.01274653586],"iteration":818,"passed_time":3.801637238,"remaining_time":0.8401664715},
{"learn":[0.01272295582],"iteration":819,"passed_time":3.805923095,"remaining_time":0.835446533},
{"learn":[0.01270364722],"iteration":820,"passed_time":3.811418511,"remaining_time":0.8309913684},
{"learn":[0.01268395131],"iteration":821,"passed_time":3.815933665,"remaining_time":0.8263214018},
{"learn":[0.01265639584],"iteration":822,"passed_time":3.820654333,"remaining_time":0.8216960109},
{"learn":[0.01263987243],"iteration":823,"passed_time":3.826258208,"remaining_time":0.8172590348},
{"learn":[0.01262245631],"iteration":824,"passed_time":3.830038348,"remaining_time":0.8124323769},
{"learn":[0.01260494389],"iteration":825,"passed_time":3.833758701,"remaining_time":0.8075956586},
{"learn":[0.01256607329],"iteration":826,"passed_time":3.838692185,"remaining_time":0.8030154148},
{"learn":[0.01253807288],"iteration":827,"passed_time":3.842398487,"remaining_time":0.7981793959},
{"learn":[0.01250175181],"iteration":828,"passed_time":3.846040174,"remaining_time":0.7933327742},
{"learn":[0.01246706756],"iteration":829,"passed_time":3.849748854,"remaining_time":0.7885027773},
{"learn":[0.01243659415],"iteration":830,"passed_time":3.854668988,"remaining_time":0.7839218519},
{"learn":[0.01240762164],"iteration":831,"passed_time":3.858404206,"remaining_time":0.7791008492},
{"learn":[0.01238397717],"iteration":832,"passed_time":3.862093108,"remaining_time":0.7742731682},
{"learn":[0.01236575897],"iteration":833,"passed_time":3.865734701,"remaining_time":0.7694388013},
{"learn":[0.0123459463],"iteration":834,"passed_time":3.871603166,"remaining_time":0.7650473322},
{"learn":[0.01232372426],"iteration":835,"passed_time":3.875520059,"remaining_time":0.7602694853},
{"learn":[0.0123057682],"iteration":836,"passed_time":3.879227583,"remaining_time":0.7554529223},
{"learn":[0.01228666479],"iteration":837,"passed_time":3.882934788,"remaining_time":0.7506389447},
{"learn":[0.01226400172],"iteration":838,"passed_time":3.887500452,"remaining_time":0.7459923394},
{"learn":[0.01224631218],"iteration":839,"passed_time":3.891140247,"remaining_time":0.7411695709},
{"learn":[0.01221426913],"iteration":840,"passed_time":3.894786757,"remaining_time":0.7363508851},
{"learn":[0.01219854052],"iteration":841,"passed_time":3.899732329,"remaining_time":0.7317787505},
{"learn":[0.01216757545],"iteration":842,"passed_time":3.90453928,"remaining_time":0.7271799133},
{"learn":[0.01215030945],"iteration":843,"passed_time":3.908170661,"remaining_time":0.7223632975},
{"learn":[0.01213083092],"iteration":844,"passed_time":3.911749271,"remaining_time":0.717539807},
{"learn":[0.01210726273],"iteration":845,"passed_time":3.924033297,"remaining_time":0.7143039335},
{"learn":[0.01207933843],"iteration":846,"passed_time":3.927947277,"remaining_time":0.7095347502},
{"learn":[0.01205619538],"iteration":847,"passed_time":3.932032138,"remaining_time":0.7047982134},
{"learn":[0.01203675496],"iteration":848,"passed_time":3.93664135,"remaining_time":0.7001564709},
{"learn":[0.01200704446],"iteration":849,"passed_time":3.940288989,"remaining_time":0.6953451157},
{"learn":[0.01197999832],"iteration":850,"passed_time":3.943964211,"remaining_time":0.6905413249},
{"learn":[0.01195659642],"iteration":851,"passed_time":3.948549861,"remaining_time":0.6858983327},
{"learn":[0.01193966817],"iteration":852,"passed_time":3.953910787,"remaining_time":0.6813890806},
{"learn":[0.01192387739],"iteration":853,"passed_time":3.959101028,"remaining_time":0.6768486535},
{"learn":[0.01189479514],"iteration":854,"passed_time":3.964442561,"remaining_time":0.6723323641},
{"learn":[0.01187115927],"iteration":855,"passed_time":3.96943157,"remaining_time":0.6677548436},
{"learn":[0.01186013351],"iteration":856,"passed_time":3.974256102,"remaining_time":0.6631489178},
{"learn":[0.01183023096],"iteration":857,"passed_time":3.979444988,"remaining_time":0.6586027836},
{"learn":[0.01180706974],"iteration":858,"passed_time":3.984502798,"remaining_time":0.6540336374},
{"learn":[0.01179581658],"iteration":859,"passed_time":3.989006475,"remaining_time":0.6493731472},
{"learn":[0.0117688063],"iteration":860,"passed_time":3.993341585,"remaining_time":0.6446858076},
{"learn":[0.01175707832],"iteration":861,"passed_time":3.99945964,"remaining_time":0.6402847219},
{"learn":[0.01175186103],"iteration":862,"passed_time":4.004632627,"remaining_time":0.6357296291},
{"learn":[0.01173809538],"iteration":863,"passed_time":4.009344827,"remaining_time":0.6311005747},
{"learn":[0.0117087746],"iteration":864,"passed_time":4.014956943,"remaining_time":0.6266117773},
{"learn":[0.01169171346],"iteration":865,"passed_time":4.020058205,"remaining_time":0.6220413389},
{"learn":[0.01166622462],"iteration":866,"passed_time":4.024617059,"remaining_time":0.6173864692},
{"learn":[0.01162781476],"iteration":867,"passed_time":4.02960956,"remaining_time":0.6127977671},
{"learn":[0.01160591264],"iteration":868,"passed_time":4.033873817,"remaining_time":0.6080983544},
{"learn":[0.01157417689],"iteration":869,"passed_time":4.0375489,"remaining_time":0.6033119045},
{"learn":[0.01155437843],"iteration":870,"passed_time":4.041165638,"remaining_time":0.5985193655},
{"learn":[0.01153236307],"iteration":871,"passed_time":4.046307738,"remaining_time":0.5939534294},
{"learn":[0.01151527348],"iteration":872,"passed_time":4.050241558,"remaining_time":0.5892103984},
{"learn":[0.0114851383],"iteration":873,"passed_time":4.053963967,"remaining_time":0.5844387412},
{"learn":[0.01146164159],"iteration":874,"passed_time":4.057627489,"remaining_time":0.5796610699},
{"learn":[0.01143199097],"iteration":875,"passed_time":4.062525273,"remaining_time":0.575060655},
{"learn":[0.01140136474],"iteration":876,"passed_time":4.066361104,"remaining_time":0.5703106223},
{"learn":[0.0113797873],"iteration":877,"passed_time":4.070074897,"remaining_time":0.5655457146},
{"learn":[0.01136463842],"iteration":878,"passed_time":4.073726743,"remaining_time":0.5607746711},
{"learn":[0.0113442279],"iteration":879,"passed_time":4.078584697,"remaining_time":0.5561706405},
{"learn":[0.0113189754],"iteration":880,"passed_time":4.082454469,"remaining_time":0.551432556},
{"learn":[0.01130294259],"iteration":881,"passed_time":4.086248706,"remaining_time":0.5466863349},
{"learn":[0.01128192336],"iteration":882,"passed_time":4.089970264,"remaining_time":0.5419326398},
{"learn":[0.01126747614],"iteration":883,"passed_time":4.096239861,"remaining_time":0.5375156379},
{"learn":[0.01124138713],"iteration":884,"passed_time":4.101136863,"remaining_time":0.5329160896},
{"learn":[0.01122081444],"iteration":885,"passed_time":4.105085256,"remaining_time":0.528193814},
{"learn":[0.01119631745],"iteration":886,"passed_time":4.110505148,"remaining_time":0.5236607461},
{"learn":[0.01116714521],"iteration":887,"passed_time":4.11616,"remaining_time":0.5191553153},
{"learn":[0.01113883286],"iteration":888,"passed_time":4.12052313,"remaining_time":0.5144860151},
{"learn":[0.01111274553],"iteration":889,"passed_time":4.12470173,"remaining_time":0.5097945958},
{"learn":[0.01108423978],"iteration":890,"passed_time":4.130272141,"remaining_time":0.5052745942},
{"learn":[0.01106582882],"iteration":891,"passed_time":4.134759709,"remaining_time":0.5006211307},
{"learn":[0.01104996194],"iteration":892,"passed_time":4.13852587,"remaining_time":0.4958815992},
{"learn":[0.01102613014],"iteration":893,"passed_time":4.143681017,"remaining_time":0.491308935},
{"learn":[0.01099969673],"iteration":894,"passed_time":4.147452354,"remaining_time":0.4865726225},
{"learn":[0.01097382235],"iteration":895,"passed_time":4.151111262,"remaining_time":0.4818254143},
{"learn":[0.01095595545],"iteration":896,"passed_time":4.154934784,"remaining_time":0.4770995349},
{"learn":[0.01094607214],"iteration":897,"passed_time":4.159920777,"remaining_time":0.4725077052},
{"learn":[0.01092379768],"iteration":898,"passed_time":4.16379628,"remaining_time":0.4677902384},
{"learn":[0.01090333165],"iteration":899,"passed_time":4.167495003,"remaining_time":0.4630550003},
{"learn":[0.01088490075],"iteration":900,"passed_time":4.171369663,"remaining_time":0.4583413948},
{"learn":[0.01086449211],"iteration":901,"passed_time":4.176294116,"remaining_time":0.4537437066},
{"learn":[0.0108464112],"iteration":902,"passed_time":4.180111638,"remaining_time":0.4490263886},
{"learn":[0.01083700356],"iteration":903,"passed_time":4.183872423,"remaining_time":0.4443050361},
{"learn":[0.01081456296],"iteration":904,"passed_time":4.187823491,"remaining_time":0.4396057809},
{"learn":[0.01079374043],"iteration":905,"passed_time":4.192625088,"remaining_time":0.4349964219},
{"learn":[0.0107684752],"iteration":906,"passed_time":4.196382974,"remaining_time":0.4302796213},
{"learn":[0.01075380912],"iteration":907,"passed_time":4.200078941,"remaining_time":0.4255586592},
{"learn":[0.01073115108],"iteration":908,"passed_time":4.204030657,"remaining_time":0.4208655553},
{"learn":[0.01071804547],"iteration":909,"passed_time":4.208681585,"remaining_time":0.4162432337},
{"learn":[0.01068819672],"iteration":910,"passed_time":4.212487776,"remaining_time":0.4115383228},
{"learn":[0.01065996779],"iteration":911,"passed_time":4.216271944,"remaining_time":0.4068332578},
{"learn":[0.01063247442],"iteration":912,"passed_time":4.221006276,"remaining_time":0.4022207514},
{"learn":[0.01061312931],"iteration":913,"passed_time":4.225431141,"remaining_time":0.3975788601},
{"learn":[0.01059285349],"iteration":914,"passed_time":4.229423474,"remaining_time":0.3928972626},
{"learn":[0.01057748676],"iteration":915,"passed_time":4.23362211,"remaining_time":0.3882360887},
{"learn":[0.01055874016],"iteration":916,"passed_time":4.238536045,"remaining_time":0.3836406671},
{"learn":[0.01054492845],"iteration":917,"passed_time":4.243599795,"remaining_time":0.3790579338},
{"learn":[0.01052464577],"iteration":918,"passed_time":4.247723987,"remaining_time":0.3743913416},
{"learn":[0.01050342069],"iteration":919,"passed_time":4.252330018,"remaining_time":0.3697678277},
{"learn":[0.01048503074],"iteration":920,"passed_time":4.257618768,"remaining_time":0.3652029128},
{"learn":[0.01046880884],"iteration":921,"passed_time":4.261920461,"remaining_time":0.360552924},
{"learn":[0.01043827749],"iteration":922,"passed_time":4.267245049,"remaining_time":0.3559890236},
{"learn":[0.01042818092],"iteration":923,"passed_time":4.273224318,"remaining_time":0.3514773248},
{"learn":[0.0104197666],"iteration":924,"passed_time":4.277861624,"remaining_time":0.3468536452},
{"learn":[0.01040170885],"iteration":925,"passed_time":4.282391136,"remaining_time":0.3422213219},
{"learn":[0.0103869407],"iteration":926,"passed_time":4.287927188,"remaining_time":0.337668484},
{"learn":[0.01036374166],"iteration":927,"passed_time":4.293036404,"remaining_time":0.3330804107},
{"learn":[0.01033560468],"iteration":928,"passed_time":4.298035145,"remaining_time":0.3284827721},
{"learn":[0.01030624489],"iteration":929,"passed_time":4.304157049,"remaining_time":0.3239688101},
{"learn":[0.01028953405],"iteration":930,"passed_time":4.309272693,"remaining_time":0.3193768162},
{"learn":[0.01027524276],"iteration":931,"passed_time":4.313361464,"remaining_time":0.3147087764},
{"learn":[0.0102554221],"iteration":932,"passed_time":4.318066689,"remaining_time":0.3100862467},
{"learn":[0.01022928822],"iteration":933,"passed_time":4.324503469,"remaining_time":0.3055858982},
{"learn":[0.01020560832],"iteration":934,"passed_time":4.328488677,"remaining_time":0.3009109775},
{"learn":[0.01018909409],"iteration":935,"passed_time":4.333099286,"remaining_time":0.2962802931},
{"learn":[0.01016928788],"iteration":936,"passed_time":4.337969218,"remaining_time":0.2916670872},
{"learn":[0.01014667487],"iteration":937,"passed_time":4.341802866,"remaining_time":0.2869848376},
{"learn":[0.01012842898],"iteration":938,"passed_time":4.345837022,"remaining_time":0.282317421},
{"learn":[0.01009798332],"iteration":939,"passed_time":4.350739247,"remaining_time":0.2777067605},
{"learn":[0.01007886175],"iteration":940,"passed_time":4.355269759,"remaining_time":0.273072174},
{"learn":[0.01005210664],"iteration":941,"passed_time":4.35953209,"remaining_time":0.2684212964},
{"learn":[0.01003349201],"iteration":942,"passed_time":4.363323242,"remaining_time":0.2637427623},
{"learn":[0.010006995],"iteration":943,"passed_time":4.369066113,"remaining_time":0.2591818881},
{"learn":[0.009987478046],"iteration":944,"passed_time":4.373229434,"remaining_time":0.2545265808},
{"learn":[0.009966094765],"iteration":945,"passed_time":4.377007559,"remaining_time":0.2498503258},
{"learn":[0.009952737158],"iteration":946,"passed_time":4.38168661,"remaining_time":0.2452263889},
{"learn":[0.009933441036],"iteration":947,"passed_time":4.386667511,"remaining_time":0.240618893},
{"learn":[0.009922477605],"iteration":948,"passed_time":4.391582325,"remaining_time":0.2360070585},
{"learn":[0.009895179951],"iteration":949,"passed_time":4.395763154,"remaining_time":0.2313559555},
{"learn":[0.009879416733],"iteration":950,"passed_time":4.400980157,"remaining_time":0.22675923},
{"learn":[0.009867189849],"iteration":951,"passed_time":4.40495871,"remaining_time":0.2220987585},
{"learn":[0.009850684617],"iteration":952,"passed_time":4.409321225,"remaining_time":0.2174586543},
{"learn":[0.009836789812],"iteration":953,"passed_time":4.41567982,"remaining_time":0.2129153792},
{"learn":[0.009814766704],"iteration":954,"passed_time":4.42017709,"remaining_time":0.2082805959},
{"learn":[0.009804199544],"iteration":955,"passed_time":4.42419365,"remaining_time":0.2036239755},
{"learn":[0.00979647996],"iteration":956,"passed_time":4.428587315,"remaining_time":0.1989856369},
{"learn":[0.009780925797],"iteration":957,"passed_time":4.433478243,"remaining_time":0.1943696098},
{"learn":[0.00976333871],"iteration":958,"passed_time":4.437609353,"remaining_time":0.189720525},
{"learn":[0.009744353418],"iteration":959,"passed_time":4.441317351,"remaining_time":0.1850548896},
{"learn":[0.009724216763],"iteration":960,"passed_time":4.446306089,"remaining_time":0.1804432232},
{"learn":[0.009706504919],"iteration":961,"passed_time":4.450705325,"remaining_time":0.1758074869},
{"learn":[0.009685630515],"iteration":962,"passed_time":4.454490412,"remaining_time":0.1711486451},
{"learn":[0.009665384387],"iteration":963,"passed_time":4.45852173,"remaining_time":0.1665008115},
{"learn":[0.009649747774],"iteration":964,"passed_time":4.464369194,"remaining_time":0.1619201262},
{"learn":[0.009628878673],"iteration":965,"passed_time":4.468252892,"remaining_time":0.1572677001},
{"learn":[0.009610150102],"iteration":966,"passed_time":4.472339755,"remaining_time":0.1526237972},
{"learn":[0.009586149268],"iteration":967,"passed_time":4.476570711,"remaining_time":0.1479858086},
{"learn":[0.009563569418],"iteration":968,"passed_time":4.481357807,"remaining_time":0.143366452},
{"learn":[0.009546175701],"iteration":969,"passed_time":4.485522071,"remaining_time":0.1387274867},
{"learn":[0.009525075702],"iteration":970,"passed_time":4.489226319,"remaining_time":0.1340757603},
{"learn":[0.00950269128],"iteration":971,"passed_time":4.495568849,"remaining_time":0.1295019833},
{"learn":[0.009485007153],"iteration":972,"passed_time":4.500373938,"remaining_time":0.1248819078},
{"learn":[0.009467984834],"iteration":973,"passed_time":4.504164111,"remaining_time":0.1202343603},
{"learn":[0.00945953256],"iteration":974,"passed_time":4.509131248,"remaining_time":0.1156187499},
{"learn":[0.009441882454],"iteration":975,"passed_time":4.515402112,"remaining_time":0.1110344782},
{"learn":[0.009440654205],"iteration":976,"passed_time":4.520906334,"remaining_time":0.1064287059},
{"learn":[0.009438310891],"iteration":977,"passed_time":4.526437233,"remaining_time":0.1018216964},
{"learn":[0.00941415056],"iteration":978,"passed_time":4.530670401,"remaining_time":0.09718496264},
{"learn":[0.009392842288],"iteration":979,"passed_time":4.534752059,"remaining_time":0.0925459604},
{"learn":[0.00937089891],"iteration":980,"passed_time":4.538509053,"remaining_time":0.08790180633},
{"learn":[0.009356189777],"iteration":981,"passed_time":4.544419399,"remaining_time":0.08329892992},
{"learn":[0.009343089124],"iteration":982,"passed_time":4.548770818,"remaining_time":0.07866643327},
{"learn":[0.00932762894],"iteration":983,"passed_time":4.552435397,"remaining_time":0.07402333979},
{"learn":[0.009302605936],"iteration":984,"passed_time":4.557123394,"remaining_time":0.06939781819},
{"learn":[0.009279755699],"iteration":985,"passed_time":4.56194383,"remaining_time":0.06477405033},
{"learn":[0.009266113604],"iteration":986,"passed_time":4.565859929,"remaining_time":0.06013797272},
{"learn":[0.009249953541],"iteration":987,"passed_time":4.569810035,"remaining_time":0.05550376561},
{"learn":[0.009229082948],"iteration":988,"passed_time":4.575261543,"remaining_time":0.05088764102},
{"learn":[0.009202668867],"iteration":989,"passed_time":4.579435776,"remaining_time":0.04625692703},
{"learn":[0.009177548659],"iteration":990,"passed_time":4.583597782,"remaining_time":0.04162702324},
{"learn":[0.00915926169],"iteration":991,"passed_time":4.58802331,"remaining_time":0.03700018798},
{"learn":[0.00914466703],"iteration":992,"passed_time":4.593845348,"remaining_time":0.03238360265},
{"learn":[0.009123590971],"iteration":993,"passed_time":4.598012476,"remaining_time":0.02775460247},
{"learn":[0.009098014845],"iteration":994,"passed_time":4.601780381,"remaining_time":0.02312452453},
{"learn":[0.009081175839],"iteration":995,"passed_time":4.607563248,"remaining_time":0.01850427007},
{"learn":[0.009059860899],"iteration":996,"passed_time":4.612052242,"remaining_time":0.0138777901},
{"learn":[0.009042476617],"iteration":997,"passed_time":4.615862826,"remaining_time":0.009250226104},
{"learn":[0.00902069971],"iteration":998,"passed_time":4.619840585,"remaining_time":0.00462446505},
{"learn":[0.008999264349],"iteration":999,"passed_time":4.624670401,"remaining_time":0}
]}